{"Name":"dd","Variations":{"dd":{"Variation":null,"Mentions":0,"Refs":[{"Title":"User Page: Peter Geelen - TechNet Articles - United States (English) - TechNet Wiki","FileName":"31390.user-page-peter-geelen.html","Mentions":4},{"Title":"User Page: Peter Laker - TechNet Articles - United States (English) - TechNet Wiki","FileName":"52493.user-page-peter-laker.html","Mentions":2}]},"DD":{"Variation":null,"Mentions":0,"Refs":[{"Title":"IoT Suite - Under The Hood - Remote Monitoring - TechNet Articles - United States (English) - TechNet Wiki","FileName":"32941.iot-suite-under-the-hood-remote-monitoring.html","Mentions":6}]}},"FileName":"dd.json","Refs":[{"Title":"User Page: Peter Geelen - TechNet Articles - United States (English) - TechNet Wiki","FileName":"31390.user-page-peter-geelen.html","Mentions":4},{"Title":"User Page: Peter Laker - TechNet Articles - United States (English) - TechNet Wiki","FileName":"52493.user-page-peter-laker.html","Mentions":2},{"Title":"IoT Suite - Under The Hood - Remote Monitoring - TechNet Articles - United States (English) - TechNet Wiki","FileName":"32941.iot-suite-under-the-hood-remote-monitoring.html","Mentions":6}],"ShowAsTag":false,"IsPersonalised":false,"Mentions":12,"Notes":null}