{"Title":"TechNet Guru Contributions - May 2015 - TechNet Articles - United States (English) - TechNet Wiki","FromPage":"https://social.technet.microsoft.com/wiki/contents/articles/30963.technet-guru-contributions-may-2015.aspx","CreatedBy":{"UserGuid":"902caf78-af24-4b99-8e39-eeffc5fc9331","Name":"Pete Laker","Url":"/wiki/149154/ProfileUrlRedirect.ashx","AvatarHtml":"<img src=\"https://i1.social.s-msft.com:443/profile/u/avatar.jpg?displayname=pete+laker&amp;size=large\" alt=\"\" style=\"border-width:0px;max-height:27px;max-width:27px;\" />\t\r\n\t\t\t\t        ","Affiliations":"(MVP, Microsoft Partner, Microsoft Community Contributor)","RevisionDate":"3 May 2015 12:06 PM"},"RevisedBy":{"UserGuid":"902caf78-af24-4b99-8e39-eeffc5fc9331","Name":"Pete Laker","Url":"/wiki/149154/ProfileUrlRedirect.ashx","AvatarHtml":"<img src=\"https://i1.social.s-msft.com:443/profile/u/avatar.jpg?displayname=pete+laker&amp;size=large\" alt=\"\" style=\"border-width:0px;max-height:27px;max-width:27px;\" />\r\n\t\t\t\t\t\t        ","Affiliations":"(MVP, Microsoft Partner, Microsoft Community Contributor)","RevisionDate":"23 Jun 2015 12:58 PM"},"Revisions":63,"Comments":30,"Language":null,"Iso6391Name":"en","KeyPhrases":[{"Name":"TechNet Guru Contributions - May 2015 - TechNet Articles - United States (English) - TechNet Wiki","SafeName":"account","TallyMentions":0,"TallyArticles":0,"ShowAsTag":false,"IsPersonalised":false},{"Name":"TechNet Guru Contributions - May 2015 - TechNet Articles - United States (English) - TechNet Wiki","SafeName":"acknowledgement","TallyMentions":0,"TallyArticles":0,"ShowAsTag":false,"IsPersonalised":false},{"Name":"TechNet Guru Contributions - May 2015 - TechNet Articles - United States (English) - TechNet Wiki","SafeName":"admin","TallyMentions":0,"TallyArticles":0,"ShowAsTag":false,"IsPersonalised":false},{"Name":"TechNet Guru Contributions - May 2015 - TechNet Articles - United States (English) - TechNet Wiki","SafeName":"administration component","TallyMentions":0,"TallyArticles":0,"ShowAsTag":false,"IsPersonalised":false},{"Name":"TechNet Guru Contributions - May 2015 - TechNet Articles - United States (English) - TechNet Wiki","SafeName":"adoration","TallyMentions":0,"TallyArticles":0,"ShowAsTag":false,"IsPersonalised":false},{"Name":"TechNet Guru Contributions - May 2015 - TechNet Articles - United States (English) - TechNet Wiki","SafeName":"alsothis month","TallyMentions":0,"TallyArticles":0,"ShowAsTag":false,"IsPersonalised":false},{"Name":"TechNet Guru Contributions - May 2015 - TechNet Articles - United States (English) - TechNet Wiki","SafeName":"amp","TallyMentions":0,"TallyArticles":0,"ShowAsTag":false,"IsPersonalised":false},{"Name":"TechNet Guru Contributions - May 2015 - TechNet Articles - United States (English) - TechNet Wiki","SafeName":"andy","TallyMentions":0,"TallyArticles":0,"ShowAsTag":false,"IsPersonalised":false},{"Name":"TechNet Guru Contributions - May 2015 - TechNet Articles - United States (English) - TechNet Wiki","SafeName":"andy oneill","TallyMentions":0,"TallyArticles":0,"ShowAsTag":false,"IsPersonalised":false},{"Name":"TechNet Guru Contributions - May 2015 - TechNet Articles - United States (English) - TechNet Wiki","SafeName":"announcement","TallyMentions":0,"TallyArticles":0,"ShowAsTag":false,"IsPersonalised":false},{"Name":"TechNet Guru Contributions - May 2015 - TechNet Articles - United States (English) - TechNet Wiki","SafeName":"app development","TallyMentions":0,"TallyArticles":0,"ShowAsTag":false,"IsPersonalised":false},{"Name":"TechNet Guru Contributions - May 2015 - TechNet Articles - United States (English) - TechNet Wiki","SafeName":"appropriate section","TallyMentions":0,"TallyArticles":0,"ShowAsTag":false,"IsPersonalised":false},{"Name":"TechNet Guru Contributions - May 2015 - TechNet Articles - United States (English) - TechNet Wiki","SafeName":"arduino uno","TallyMentions":0,"TallyArticles":0,"ShowAsTag":false,"IsPersonalised":false},{"Name":"TechNet Guru Contributions - May 2015 - TechNet Articles - United States (English) - TechNet Wiki","SafeName":"aren","TallyMentions":0,"TallyArticles":0,"ShowAsTag":false,"IsPersonalised":false},{"Name":"TechNet Guru Contributions - May 2015 - TechNet Articles - United States (English) - TechNet Wiki","SafeName":"arleta wanat","TallyMentions":0,"TallyArticles":0,"ShowAsTag":false,"IsPersonalised":false},{"Name":"TechNet Guru Contributions - May 2015 - TechNet Articles - United States (English) - TechNet Wiki","SafeName":"article","TallyMentions":0,"TallyArticles":0,"ShowAsTag":false,"IsPersonalised":false},{"Name":"TechNet Guru Contributions - May 2015 - TechNet Articles - United States (English) - TechNet Wiki","SafeName":"article title","TallyMentions":0,"TallyArticles":0,"ShowAsTag":false,"IsPersonalised":false},{"Name":"TechNet Guru Contributions - May 2015 - TechNet Articles - United States (English) - TechNet Wiki","SafeName":"articles","TallyMentions":0,"TallyArticles":0,"ShowAsTag":false,"IsPersonalised":false},{"Name":"TechNet Guru Contributions - May 2015 - TechNet Articles - United States (English) - TechNet Wiki","SafeName":"author","TallyMentions":0,"TallyArticles":0,"ShowAsTag":false,"IsPersonalised":false},{"Name":"TechNet Guru Contributions - May 2015 - TechNet Articles - United States (English) - TechNet Wiki","SafeName":"author profile urls","TallyMentions":0,"TallyArticles":0,"ShowAsTag":false,"IsPersonalised":false},{"Name":"TechNet Guru Contributions - May 2015 - TechNet Articles - United States (English) - TechNet Wiki","SafeName":"awards","TallyMentions":0,"TallyArticles":0,"ShowAsTag":false,"IsPersonalised":false},{"Name":"TechNet Guru Contributions - May 2015 - TechNet Articles - United States (English) - TechNet Wiki","SafeName":"azure","TallyMentions":0,"TallyArticles":0,"ShowAsTag":false,"IsPersonalised":false},{"Name":"TechNet Guru Contributions - May 2015 - TechNet Articles - United States (English) - TechNet Wiki","SafeName":"azure contribution","TallyMentions":0,"TallyArticles":0,"ShowAsTag":false,"IsPersonalised":false},{"Name":"TechNet Guru Contributions - May 2015 - TechNet Articles - United States (English) - TechNet Wiki","SafeName":"azure service portals","TallyMentions":0,"TallyArticles":0,"ShowAsTag":false,"IsPersonalised":false},{"Name":"TechNet Guru Contributions - May 2015 - TechNet Articles - United States (English) - TechNet Wiki","SafeName":"azure virtual machines","TallyMentions":0,"TallyArticles":0,"ShowAsTag":false,"IsPersonalised":false},{"Name":"TechNet Guru Contributions - May 2015 - TechNet Articles - United States (English) - TechNet Wiki","SafeName":"bi contribution","TallyMentions":0,"TallyArticles":0,"ShowAsTag":false,"IsPersonalised":false},{"Name":"TechNet Guru Contributions - May 2015 - TechNet Articles - United States (English) - TechNet Wiki","SafeName":"big data analytics","TallyMentions":0,"TallyArticles":0,"ShowAsTag":false,"IsPersonalised":false},{"Name":"TechNet Guru Contributions - May 2015 - TechNet Articles - United States (English) - TechNet Wiki","SafeName":"biztalk","TallyMentions":0,"TallyArticles":0,"ShowAsTag":false,"IsPersonalised":false},{"Name":"TechNet Guru Contributions - May 2015 - TechNet Articles - United States (English) - TechNet Wiki","SafeName":"biztalk contribution","TallyMentions":0,"TallyArticles":0,"ShowAsTag":false,"IsPersonalised":false},{"Name":"TechNet Guru Contributions - May 2015 - TechNet Articles - United States (English) - TechNet Wiki","SafeName":"biztalk devops","TallyMentions":0,"TallyArticles":0,"ShowAsTag":false,"IsPersonalised":false},{"Name":"TechNet Guru Contributions - May 2015 - TechNet Articles - United States (English) - TechNet Wiki","SafeName":"biztalk environment","TallyMentions":0,"TallyArticles":0,"ShowAsTag":false,"IsPersonalised":false},{"Name":"TechNet Guru Contributions - May 2015 - TechNet Articles - United States (English) - TechNet Wiki","SafeName":"biztalk health monitor","TallyMentions":0,"TallyArticles":0,"ShowAsTag":false,"IsPersonalised":false},{"Name":"TechNet Guru Contributions - May 2015 - TechNet Articles - United States (English) - TechNet Wiki","SafeName":"blend","TallyMentions":0,"TallyArticles":0,"ShowAsTag":false,"IsPersonalised":false},{"Name":"TechNet Guru Contributions - May 2015 - TechNet Articles - United States (English) - TechNet Wiki","SafeName":"blog","TallyMentions":0,"TallyArticles":0,"ShowAsTag":false,"IsPersonalised":false},{"Name":"TechNet Guru Contributions - May 2015 - TechNet Articles - United States (English) - TechNet Wiki","SafeName":"blog posts","TallyMentions":0,"TallyArticles":0,"ShowAsTag":false,"IsPersonalised":false},{"Name":"TechNet Guru Contributions - May 2015 - TechNet Articles - United States (English) - TechNet Wiki","SafeName":"bulk override creation","TallyMentions":0,"TallyArticles":0,"ShowAsTag":false,"IsPersonalised":false},{"Name":"TechNet Guru Contributions - May 2015 - TechNet Articles - United States (English) - TechNet Wiki","SafeName":"c# contribution","TallyMentions":0,"TallyArticles":0,"ShowAsTag":false,"IsPersonalised":false},{"Name":"TechNet Guru Contributions - May 2015 - TechNet Articles - United States (English) - TechNet Wiki","SafeName":"carmelo","TallyMentions":0,"TallyArticles":0,"ShowAsTag":false,"IsPersonalised":false},{"Name":"TechNet Guru Contributions - May 2015 - TechNet Articles - United States (English) - TechNet Wiki","SafeName":"categories","TallyMentions":0,"TallyArticles":0,"ShowAsTag":false,"IsPersonalised":false},{"Name":"TechNet Guru Contributions - May 2015 - TechNet Articles - United States (English) - TechNet Wiki","SafeName":"category","TallyMentions":0,"TallyArticles":0,"ShowAsTag":false,"IsPersonalised":false},{"Name":"TechNet Guru Contributions - May 2015 - TechNet Articles - United States (English) - TechNet Wiki","SafeName":"chart control","TallyMentions":0,"TallyArticles":0,"ShowAsTag":false,"IsPersonalised":false},{"Name":"TechNet Guru Contributions - May 2015 - TechNet Articles - United States (English) - TechNet Wiki","SafeName":"cluster nodes","TallyMentions":0,"TallyArticles":0,"ShowAsTag":false,"IsPersonalised":false},{"Name":"TechNet Guru Contributions - May 2015 - TechNet Articles - United States (English) - TechNet Wiki","SafeName":"comment","TallyMentions":0,"TallyArticles":0,"ShowAsTag":false,"IsPersonalised":false},{"Name":"TechNet Guru Contributions - May 2015 - TechNet Articles - United States (English) - TechNet Wiki","SafeName":"community member","TallyMentions":0,"TallyArticles":0,"ShowAsTag":false,"IsPersonalised":false},{"Name":"TechNet Guru Contributions - May 2015 - TechNet Articles - United States (English) - TechNet Wiki","SafeName":"computer","TallyMentions":0,"TallyArticles":0,"ShowAsTag":false,"IsPersonalised":false},{"Name":"TechNet Guru Contributions - May 2015 - TechNet Articles - United States (English) - TechNet Wiki","SafeName":"configmgr data","TallyMentions":0,"TallyArticles":0,"ShowAsTag":false,"IsPersonalised":false},{"Name":"TechNet Guru Contributions - May 2015 - TechNet Articles - United States (English) - TechNet Wiki","SafeName":"console mode","TallyMentions":0,"TallyArticles":0,"ShowAsTag":false,"IsPersonalised":false},{"Name":"TechNet Guru Contributions - May 2015 - TechNet Articles - United States (English) - TechNet Wiki","SafeName":"contribution","TallyMentions":0,"TallyArticles":0,"ShowAsTag":false,"IsPersonalised":false},{"Name":"TechNet Guru Contributions - May 2015 - TechNet Articles - United States (English) - TechNet Wiki","SafeName":"contributions","TallyMentions":0,"TallyArticles":0,"ShowAsTag":false,"IsPersonalised":false},{"Name":"TechNet Guru Contributions - May 2015 - TechNet Articles - United States (English) - TechNet Wiki","SafeName":"credit","TallyMentions":0,"TallyArticles":0,"ShowAsTag":false,"IsPersonalised":false},{"Name":"TechNet Guru Contributions - May 2015 - TechNet Articles - United States (English) - TechNet Wiki","SafeName":"css3","TallyMentions":0,"TallyArticles":0,"ShowAsTag":false,"IsPersonalised":false},{"Name":"TechNet Guru Contributions - May 2015 - TechNet Articles - United States (English) - TechNet Wiki","SafeName":"custom list forms","TallyMentions":0,"TallyArticles":0,"ShowAsTag":false,"IsPersonalised":false},{"Name":"TechNet Guru Contributions - May 2015 - TechNet Articles - United States (English) - TechNet Wiki","SafeName":"custom statetrigger","TallyMentions":0,"TallyArticles":0,"ShowAsTag":false,"IsPersonalised":false},{"Name":"TechNet Guru Contributions - May 2015 - TechNet Articles - United States (English) - TechNet Wiki","SafeName":"dan christian","TallyMentions":0,"TallyArticles":0,"ShowAsTag":false,"IsPersonalised":false},{"Name":"TechNet Guru Contributions - May 2015 - TechNet Articles - United States (English) - TechNet Wiki","SafeName":"danish islam","TallyMentions":0,"TallyArticles":0,"ShowAsTag":false,"IsPersonalised":false},{"Name":"TechNet Guru Contributions - May 2015 - TechNet Articles - United States (English) - TechNet Wiki","SafeName":"darshana jayathilake","TallyMentions":0,"TallyArticles":0,"ShowAsTag":false,"IsPersonalised":false},{"Name":"TechNet Guru Contributions - May 2015 - TechNet Articles - United States (English) - TechNet Wiki","SafeName":"data input validation","TallyMentions":0,"TallyArticles":0,"ShowAsTag":false,"IsPersonalised":false},{"Name":"TechNet Guru Contributions - May 2015 - TechNet Articles - United States (English) - TechNet Wiki","SafeName":"database engine","TallyMentions":0,"TallyArticles":0,"ShowAsTag":false,"IsPersonalised":false},{"Name":"TechNet Guru Contributions - May 2015 - TechNet Articles - United States (English) - TechNet Wiki","SafeName":"datatable","TallyMentions":0,"TallyArticles":0,"ShowAsTag":false,"IsPersonalised":false},{"Name":"TechNet Guru Contributions - May 2015 - TechNet Articles - United States (English) - TechNet Wiki","SafeName":"dataview","TallyMentions":0,"TallyArticles":0,"ShowAsTag":false,"IsPersonalised":false},{"Name":"TechNet Guru Contributions - May 2015 - TechNet Articles - United States (English) - TechNet Wiki","SafeName":"debug","TallyMentions":0,"TallyArticles":0,"ShowAsTag":false,"IsPersonalised":false},{"Name":"TechNet Guru Contributions - May 2015 - TechNet Articles - United States (English) - TechNet Wiki","SafeName":"dedicated blog post","TallyMentions":0,"TallyArticles":0,"ShowAsTag":false,"IsPersonalised":false},{"Name":"TechNet Guru Contributions - May 2015 - TechNet Articles - United States (English) - TechNet Wiki","SafeName":"deployment","TallyMentions":0,"TallyArticles":0,"ShowAsTag":false,"IsPersonalised":false},{"Name":"TechNet Guru Contributions - May 2015 - TechNet Articles - United States (English) - TechNet Wiki","SafeName":"desktops","TallyMentions":0,"TallyArticles":0,"ShowAsTag":false,"IsPersonalised":false},{"Name":"TechNet Guru Contributions - May 2015 - TechNet Articles - United States (English) - TechNet Wiki","SafeName":"developers","TallyMentions":0,"TallyArticles":0,"ShowAsTag":false,"IsPersonalised":false},{"Name":"TechNet Guru Contributions - May 2015 - TechNet Articles - United States (English) - TechNet Wiki","SafeName":"device","TallyMentions":0,"TallyArticles":0,"ShowAsTag":false,"IsPersonalised":false},{"Name":"TechNet Guru Contributions - May 2015 - TechNet Articles - United States (English) - TechNet Wiki","SafeName":"difference","TallyMentions":0,"TallyArticles":0,"ShowAsTag":false,"IsPersonalised":false},{"Name":"TechNet Guru Contributions - May 2015 - TechNet Articles - United States (English) - TechNet Wiki","SafeName":"direct ink","TallyMentions":0,"TallyArticles":0,"ShowAsTag":false,"IsPersonalised":false},{"Name":"TechNet Guru Contributions - May 2015 - TechNet Articles - United States (English) - TechNet Wiki","SafeName":"disks","TallyMentions":0,"TallyArticles":0,"ShowAsTag":false,"IsPersonalised":false},{"Name":"TechNet Guru Contributions - May 2015 - TechNet Articles - United States (English) - TechNet Wiki","SafeName":"dpm","TallyMentions":0,"TallyArticles":0,"ShowAsTag":false,"IsPersonalised":false},{"Name":"TechNet Guru Contributions - May 2015 - TechNet Articles - United States (English) - TechNet Wiki","SafeName":"emiliano musso","TallyMentions":0,"TallyArticles":0,"ShowAsTag":false,"IsPersonalised":false},{"Name":"TechNet Guru Contributions - May 2015 - TechNet Articles - United States (English) - TechNet Wiki","SafeName":"english","TallyMentions":0,"TallyArticles":0,"ShowAsTag":false,"IsPersonalised":false},{"Name":"TechNet Guru Contributions - May 2015 - TechNet Articles - United States (English) - TechNet Wiki","SafeName":"exception","TallyMentions":0,"TallyArticles":0,"ShowAsTag":false,"IsPersonalised":false},{"Name":"TechNet Guru Contributions - May 2015 - TechNet Articles - United States (English) - TechNet Wiki","SafeName":"experiences","TallyMentions":0,"TallyArticles":0,"ShowAsTag":false,"IsPersonalised":false},{"Name":"TechNet Guru Contributions - May 2015 - TechNet Articles - United States (English) - TechNet Wiki","SafeName":"external forum","TallyMentions":0,"TallyArticles":0,"ShowAsTag":false,"IsPersonalised":false},{"Name":"TechNet Guru Contributions - May 2015 - TechNet Articles - United States (English) - TechNet Wiki","SafeName":"external list","TallyMentions":0,"TallyArticles":0,"ShowAsTag":false,"IsPersonalised":false},{"Name":"TechNet Guru Contributions - May 2015 - TechNet Articles - United States (English) - TechNet Wiki","SafeName":"ezra94","TallyMentions":0,"TallyArticles":0,"ShowAsTag":false,"IsPersonalised":false},{"Name":"TechNet Guru Contributions - May 2015 - TechNet Articles - United States (English) - TechNet Wiki","SafeName":"farm","TallyMentions":0,"TallyArticles":0,"ShowAsTag":false,"IsPersonalised":false},{"Name":"TechNet Guru Contributions - May 2015 - TechNet Articles - United States (English) - TechNet Wiki","SafeName":"filter csv files","TallyMentions":0,"TallyArticles":0,"ShowAsTag":false,"IsPersonalised":false},{"Name":"TechNet Guru Contributions - May 2015 - TechNet Articles - United States (English) - TechNet Wiki","SafeName":"fim contribution","TallyMentions":0,"TallyArticles":0,"ShowAsTag":false,"IsPersonalised":false},{"Name":"TechNet Guru Contributions - May 2015 - TechNet Articles - United States (English) - TechNet Wiki","SafeName":"fixes","TallyMentions":0,"TallyArticles":0,"ShowAsTag":false,"IsPersonalised":false},{"Name":"TechNet Guru Contributions - May 2015 - TechNet Articles - United States (English) - TechNet Wiki","SafeName":"following categories","TallyMentions":0,"TallyArticles":0,"ShowAsTag":false,"IsPersonalised":false},{"Name":"TechNet Guru Contributions - May 2015 - TechNet Articles - United States (English) - TechNet Wiki","SafeName":"forefront identity manager","TallyMentions":0,"TallyArticles":0,"ShowAsTag":false,"IsPersonalised":false},{"Name":"TechNet Guru Contributions - May 2015 - TechNet Articles - United States (English) - TechNet Wiki","SafeName":"forum content","TallyMentions":0,"TallyArticles":0,"ShowAsTag":false,"IsPersonalised":false},{"Name":"TechNet Guru Contributions - May 2015 - TechNet Articles - United States (English) - TechNet Wiki","SafeName":"forums","TallyMentions":0,"TallyArticles":0,"ShowAsTag":false,"IsPersonalised":false},{"Name":"TechNet Guru Contributions - May 2015 - TechNet Articles - United States (English) - TechNet Wiki","SafeName":"forums contributions","TallyMentions":0,"TallyArticles":0,"ShowAsTag":false,"IsPersonalised":false},{"Name":"TechNet Guru Contributions - May 2015 - TechNet Articles - United States (English) - TechNet Wiki","SafeName":"forums links available","TallyMentions":0,"TallyArticles":0,"ShowAsTag":false,"IsPersonalised":false},{"Name":"TechNet Guru Contributions - May 2015 - TechNet Articles - United States (English) - TechNet Wiki","SafeName":"galileo","TallyMentions":0,"TallyArticles":0,"ShowAsTag":false,"IsPersonalised":false},{"Name":"TechNet Guru Contributions - May 2015 - TechNet Articles - United States (English) - TechNet Wiki","SafeName":"gallery","TallyMentions":0,"TallyArticles":0,"ShowAsTag":false,"IsPersonalised":false},{"Name":"TechNet Guru Contributions - May 2015 - TechNet Articles - United States (English) - TechNet Wiki","SafeName":"gallery links","TallyMentions":0,"TallyArticles":0,"ShowAsTag":false,"IsPersonalised":false},{"Name":"TechNet Guru Contributions - May 2015 - TechNet Articles - United States (English) - TechNet Wiki","SafeName":"games","TallyMentions":0,"TallyArticles":0,"ShowAsTag":false,"IsPersonalised":false},{"Name":"TechNet Guru Contributions - May 2015 - TechNet Articles - United States (English) - TechNet Wiki","SafeName":"geolocalize","TallyMentions":0,"TallyArticles":0,"ShowAsTag":false,"IsPersonalised":false},{"Name":"TechNet Guru Contributions - May 2015 - TechNet Articles - United States (English) - TechNet Wiki","SafeName":"gerry hampson","TallyMentions":0,"TallyArticles":0,"ShowAsTag":false,"IsPersonalised":false},{"Name":"TechNet Guru Contributions - May 2015 - TechNet Articles - United States (English) - TechNet Wiki","SafeName":"glory","TallyMentions":0,"TallyArticles":0,"ShowAsTag":false,"IsPersonalised":false},{"Name":"TechNet Guru Contributions - May 2015 - TechNet Articles - United States (English) - TechNet Wiki","SafeName":"hasani","TallyMentions":0,"TallyArticles":0,"ShowAsTag":false,"IsPersonalised":false},{"Name":"TechNet Guru Contributions - May 2015 - TechNet Articles - United States (English) - TechNet Wiki","SafeName":"high resolution printouts","TallyMentions":0,"TallyArticles":0,"ShowAsTag":false,"IsPersonalised":false},{"Name":"TechNet Guru Contributions - May 2015 - TechNet Articles - United States (English) - TechNet Wiki","SafeName":"hive","TallyMentions":0,"TallyArticles":0,"ShowAsTag":false,"IsPersonalised":false},{"Name":"TechNet Guru Contributions - May 2015 - TechNet Articles - United States (English) - TechNet Wiki","SafeName":"html5","TallyMentions":0,"TallyArticles":0,"ShowAsTag":false,"IsPersonalised":false},{"Name":"TechNet Guru Contributions - May 2015 - TechNet Articles - United States (English) - TechNet Wiki","SafeName":"images","TallyMentions":0,"TallyArticles":0,"ShowAsTag":false,"IsPersonalised":false},{"Name":"TechNet Guru Contributions - May 2015 - TechNet Articles - United States (English) - TechNet Wiki","SafeName":"inaccuracies","TallyMentions":0,"TallyArticles":0,"ShowAsTag":false,"IsPersonalised":false},{"Name":"TechNet Guru Contributions - May 2015 - TechNet Articles - United States (English) - TechNet Wiki","SafeName":"inderjeet","TallyMentions":0,"TallyArticles":0,"ShowAsTag":false,"IsPersonalised":false},{"Name":"TechNet Guru Contributions - May 2015 - TechNet Articles - United States (English) - TechNet Wiki","SafeName":"introduction","TallyMentions":0,"TallyArticles":0,"ShowAsTag":false,"IsPersonalised":false},{"Name":"TechNet Guru Contributions - May 2015 - TechNet Articles - United States (English) - TechNet Wiki","SafeName":"islam moisture sensor","TallyMentions":0,"TallyArticles":0,"ShowAsTag":false,"IsPersonalised":false},{"Name":"TechNet Guru Contributions - May 2015 - TechNet Articles - United States (English) - TechNet Wiki","SafeName":"johns","TallyMentions":0,"TallyArticles":0,"ShowAsTag":false,"IsPersonalised":false},{"Name":"TechNet Guru Contributions - May 2015 - TechNet Articles - United States (English) - TechNet Wiki","SafeName":"jquery","TallyMentions":0,"TallyArticles":0,"ShowAsTag":false,"IsPersonalised":false},{"Name":"TechNet Guru Contributions - May 2015 - TechNet Articles - United States (English) - TechNet Wiki","SafeName":"js","TallyMentions":0,"TallyArticles":0,"ShowAsTag":false,"IsPersonalised":false},{"Name":"TechNet Guru Contributions - May 2015 - TechNet Articles - United States (English) - TechNet Wiki","SafeName":"judges","TallyMentions":0,"TallyArticles":0,"ShowAsTag":false,"IsPersonalised":false},{"Name":"TechNet Guru Contributions - May 2015 - TechNet Articles - United States (English) - TechNet Wiki","SafeName":"keyboard users","TallyMentions":0,"TallyArticles":0,"ShowAsTag":false,"IsPersonalised":false},{"Name":"TechNet Guru Contributions - May 2015 - TechNet Articles - United States (English) - TechNet Wiki","SafeName":"kinect","TallyMentions":0,"TallyArticles":0,"ShowAsTag":false,"IsPersonalised":false},{"Name":"TechNet Guru Contributions - May 2015 - TechNet Articles - United States (English) - TechNet Wiki","SafeName":"large integer attributes","TallyMentions":0,"TallyArticles":0,"ShowAsTag":false,"IsPersonalised":false},{"Name":"TechNet Guru Contributions - May 2015 - TechNet Articles - United States (English) - TechNet Wiki","SafeName":"leverage continuum feature","TallyMentions":0,"TallyArticles":0,"ShowAsTag":false,"IsPersonalised":false},{"Name":"TechNet Guru Contributions - May 2015 - TechNet Articles - United States (English) - TechNet Wiki","SafeName":"links","TallyMentions":0,"TallyArticles":0,"ShowAsTag":false,"IsPersonalised":false},{"Name":"TechNet Guru Contributions - May 2015 - TechNet Articles - United States (English) - TechNet Wiki","SafeName":"lt","TallyMentions":0,"TallyArticles":0,"ShowAsTag":false,"IsPersonalised":false},{"Name":"TechNet Guru Contributions - May 2015 - TechNet Articles - United States (English) - TechNet Wiki","SafeName":"machine","TallyMentions":0,"TallyArticles":0,"ShowAsTag":false,"IsPersonalised":false},{"Name":"TechNet Guru Contributions - May 2015 - TechNet Articles - United States (English) - TechNet Wiki","SafeName":"markuseliasson","TallyMentions":0,"TallyArticles":0,"ShowAsTag":false,"IsPersonalised":false},{"Name":"TechNet Guru Contributions - May 2015 - TechNet Articles - United States (English) - TechNet Wiki","SafeName":"metafile","TallyMentions":0,"TallyArticles":0,"ShowAsTag":false,"IsPersonalised":false},{"Name":"TechNet Guru Contributions - May 2015 - TechNet Articles - United States (English) - TechNet Wiki","SafeName":"microsoft azure","TallyMentions":0,"TallyArticles":0,"ShowAsTag":false,"IsPersonalised":false},{"Name":"TechNet Guru Contributions - May 2015 - TechNet Articles - United States (English) - TechNet Wiki","SafeName":"microsoft credentials","TallyMentions":0,"TallyArticles":0,"ShowAsTag":false,"IsPersonalised":false},{"Name":"TechNet Guru Contributions - May 2015 - TechNet Articles - United States (English) - TechNet Wiki","SafeName":"microsoft employee smes","TallyMentions":0,"TallyArticles":0,"ShowAsTag":false,"IsPersonalised":false},{"Name":"TechNet Guru Contributions - May 2015 - TechNet Articles - United States (English) - TechNet Wiki","SafeName":"microsoft office sway","TallyMentions":0,"TallyArticles":0,"ShowAsTag":false,"IsPersonalised":false},{"Name":"TechNet Guru Contributions - May 2015 - TechNet Articles - United States (English) - TechNet Wiki","SafeName":"microsoft power bi","TallyMentions":0,"TallyArticles":0,"ShowAsTag":false,"IsPersonalised":false},{"Name":"TechNet Guru Contributions - May 2015 - TechNet Articles - United States (English) - TechNet Wiki","SafeName":"monica","TallyMentions":0,"TallyArticles":0,"ShowAsTag":false,"IsPersonalised":false},{"Name":"TechNet Guru Contributions - May 2015 - TechNet Articles - United States (English) - TechNet Wiki","SafeName":"monitors","TallyMentions":0,"TallyArticles":0,"ShowAsTag":false,"IsPersonalised":false},{"Name":"TechNet Guru Contributions - May 2015 - TechNet Articles - United States (English) - TechNet Wiki","SafeName":"month","TallyMentions":0,"TallyArticles":0,"ShowAsTag":false,"IsPersonalised":false},{"Name":"TechNet Guru Contributions - May 2015 - TechNet Articles - United States (English) - TechNet Wiki","SafeName":"mouse","TallyMentions":0,"TallyArticles":0,"ShowAsTag":false,"IsPersonalised":false},{"Name":"TechNet Guru Contributions - May 2015 - TechNet Articles - United States (English) - TechNet Wiki","SafeName":"msdn","TallyMentions":0,"TallyArticles":0,"ShowAsTag":false,"IsPersonalised":false},{"Name":"TechNet Guru Contributions - May 2015 - TechNet Articles - United States (English) - TechNet Wiki","SafeName":"multi-page dgv printing","TallyMentions":0,"TallyArticles":0,"ShowAsTag":false,"IsPersonalised":false},{"Name":"TechNet Guru Contributions - May 2015 - TechNet Articles - United States (English) - TechNet Wiki","SafeName":"multiple hosts","TallyMentions":0,"TallyArticles":0,"ShowAsTag":false,"IsPersonalised":false},{"Name":"TechNet Guru Contributions - May 2015 - TechNet Articles - United States (English) - TechNet Wiki","SafeName":"multiple languages","TallyMentions":0,"TallyArticles":0,"ShowAsTag":false,"IsPersonalised":false},{"Name":"TechNet Guru Contributions - May 2015 - TechNet Articles - United States (English) - TechNet Wiki","SafeName":"nbsp","TallyMentions":0,"TallyArticles":0,"ShowAsTag":false,"IsPersonalised":false},{"Name":"TechNet Guru Contributions - May 2015 - TechNet Articles - United States (English) - TechNet Wiki","SafeName":"new article","TallyMentions":0,"TallyArticles":0,"ShowAsTag":false,"IsPersonalised":false},{"Name":"TechNet Guru Contributions - May 2015 - TechNet Articles - United States (English) - TechNet Wiki","SafeName":"new category","TallyMentions":0,"TallyArticles":0,"ShowAsTag":false,"IsPersonalised":false},{"Name":"TechNet Guru Contributions - May 2015 - TechNet Articles - United States (English) - TechNet Wiki","SafeName":"new code","TallyMentions":0,"TallyArticles":0,"ShowAsTag":false,"IsPersonalised":false},{"Name":"TechNet Guru Contributions - May 2015 - TechNet Articles - United States (English) - TechNet Wiki","SafeName":"new technet article","TallyMentions":0,"TallyArticles":0,"ShowAsTag":false,"IsPersonalised":false},{"Name":"TechNet Guru Contributions - May 2015 - TechNet Articles - United States (English) - TechNet Wiki","SafeName":"new xaml control","TallyMentions":0,"TallyArticles":0,"ShowAsTag":false,"IsPersonalised":false},{"Name":"TechNet Guru Contributions - May 2015 - TechNet Articles - United States (English) - TechNet Wiki","SafeName":"nonki","TallyMentions":0,"TallyArticles":0,"ShowAsTag":false,"IsPersonalised":false},{"Name":"TechNet Guru Contributions - May 2015 - TechNet Articles - United States (English) - TechNet Wiki","SafeName":"note","TallyMentions":0,"TallyArticles":0,"ShowAsTag":false,"IsPersonalised":false},{"Name":"TechNet Guru Contributions - May 2015 - TechNet Articles - United States (English) - TechNet Wiki","SafeName":"oneill","TallyMentions":0,"TallyArticles":0,"ShowAsTag":false,"IsPersonalised":false},{"Name":"TechNet Guru Contributions - May 2015 - TechNet Articles - United States (English) - TechNet Wiki","SafeName":"ones","TallyMentions":0,"TallyArticles":0,"ShowAsTag":false,"IsPersonalised":false},{"Name":"TechNet Guru Contributions - May 2015 - TechNet Articles - United States (English) - TechNet Wiki","SafeName":"optimization","TallyMentions":0,"TallyArticles":0,"ShowAsTag":false,"IsPersonalised":false},{"Name":"TechNet Guru Contributions - May 2015 - TechNet Articles - United States (English) - TechNet Wiki","SafeName":"oracle database","TallyMentions":0,"TallyArticles":0,"ShowAsTag":false,"IsPersonalised":false},{"Name":"TechNet Guru Contributions - May 2015 - TechNet Articles - United States (English) - TechNet Wiki","SafeName":"orchestrations","TallyMentions":0,"TallyArticles":0,"ShowAsTag":false,"IsPersonalised":false},{"Name":"TechNet Guru Contributions - May 2015 - TechNet Articles - United States (English) - TechNet Wiki","SafeName":"original blog","TallyMentions":0,"TallyArticles":0,"ShowAsTag":false,"IsPersonalised":false},{"Name":"TechNet Guru Contributions - May 2015 - TechNet Articles - United States (English) - TechNet Wiki","SafeName":"original forum post","TallyMentions":0,"TallyArticles":0,"ShowAsTag":false,"IsPersonalised":false},{"Name":"TechNet Guru Contributions - May 2015 - TechNet Articles - United States (English) - TechNet Wiki","SafeName":"paul","TallyMentions":0,"TallyArticles":0,"ShowAsTag":false,"IsPersonalised":false},{"Name":"TechNet Guru Contributions - May 2015 - TechNet Articles - United States (English) - TechNet Wiki","SafeName":"people","TallyMentions":0,"TallyArticles":0,"ShowAsTag":false,"IsPersonalised":false},{"Name":"TechNet Guru Contributions - May 2015 - TechNet Articles - United States (English) - TechNet Wiki","SafeName":"people picker control","TallyMentions":0,"TallyArticles":0,"ShowAsTag":false,"IsPersonalised":false},{"Name":"TechNet Guru Contributions - May 2015 - TechNet Articles - United States (English) - TechNet Wiki","SafeName":"pituach","TallyMentions":0,"TallyArticles":0,"ShowAsTag":false,"IsPersonalised":false},{"Name":"TechNet Guru Contributions - May 2015 - TechNet Articles - United States (English) - TechNet Wiki","SafeName":"pooja baraskar","TallyMentions":0,"TallyArticles":0,"ShowAsTag":false,"IsPersonalised":false},{"Name":"TechNet Guru Contributions - May 2015 - TechNet Articles - United States (English) - TechNet Wiki","SafeName":"popular forums","TallyMentions":0,"TallyArticles":0,"ShowAsTag":false,"IsPersonalised":false},{"Name":"TechNet Guru Contributions - May 2015 - TechNet Articles - United States (English) - TechNet Wiki","SafeName":"portals","TallyMentions":0,"TallyArticles":0,"ShowAsTag":false,"IsPersonalised":false},{"Name":"TechNet Guru Contributions - May 2015 - TechNet Articles - United States (English) - TechNet Wiki","SafeName":"portalsmiscellaneous","TallyMentions":0,"TallyArticles":0,"ShowAsTag":false,"IsPersonalised":false},{"Name":"TechNet Guru Contributions - May 2015 - TechNet Articles - United States (English) - TechNet Wiki","SafeName":"power bi","TallyMentions":0,"TallyArticles":0,"ShowAsTag":false,"IsPersonalised":false},{"Name":"TechNet Guru Contributions - May 2015 - TechNet Articles - United States (English) - TechNet Wiki","SafeName":"power bisql server general","TallyMentions":0,"TallyArticles":0,"ShowAsTag":false,"IsPersonalised":false},{"Name":"TechNet Guru Contributions - May 2015 - TechNet Articles - United States (English) - TechNet Wiki","SafeName":"power pivot","TallyMentions":0,"TallyArticles":0,"ShowAsTag":false,"IsPersonalised":false},{"Name":"TechNet Guru Contributions - May 2015 - TechNet Articles - United States (English) - TechNet Wiki","SafeName":"powershell","TallyMentions":0,"TallyArticles":0,"ShowAsTag":false,"IsPersonalised":false},{"Name":"TechNet Guru Contributions - May 2015 - TechNet Articles - United States (English) - TechNet Wiki","SafeName":"powershell contribution","TallyMentions":0,"TallyArticles":0,"ShowAsTag":false,"IsPersonalised":false},{"Name":"TechNet Guru Contributions - May 2015 - TechNet Articles - United States (English) - TechNet Wiki","SafeName":"problem","TallyMentions":0,"TallyArticles":0,"ShowAsTag":false,"IsPersonalised":false},{"Name":"TechNet Guru Contributions - May 2015 - TechNet Articles - United States (English) - TechNet Wiki","SafeName":"problems","TallyMentions":0,"TallyArticles":0,"ShowAsTag":false,"IsPersonalised":false},{"Name":"TechNet Guru Contributions - May 2015 - TechNet Articles - United States (English) - TechNet Wiki","SafeName":"project spartan","TallyMentions":0,"TallyArticles":0,"ShowAsTag":false,"IsPersonalised":false},{"Name":"TechNet Guru Contributions - May 2015 - TechNet Articles - United States (English) - TechNet Wiki","SafeName":"questions","TallyMentions":0,"TallyArticles":0,"ShowAsTag":false,"IsPersonalised":false},{"Name":"TechNet Guru Contributions - May 2015 - TechNet Articles - United States (English) - TechNet Wiki","SafeName":"quot","TallyMentions":0,"TallyArticles":0,"ShowAsTag":false,"IsPersonalised":false},{"Name":"TechNet Guru Contributions - May 2015 - TechNet Articles - United States (English) - TechNet Wiki","SafeName":"r2","TallyMentions":0,"TallyArticles":0,"ShowAsTag":false,"IsPersonalised":false},{"Name":"TechNet Guru Contributions - May 2015 - TechNet Articles - United States (English) - TechNet Wiki","SafeName":"read copy of database","TallyMentions":0,"TallyArticles":0,"ShowAsTag":false,"IsPersonalised":false},{"Name":"TechNet Guru Contributions - May 2015 - TechNet Articles - United States (English) - TechNet Wiki","SafeName":"richard mueller","TallyMentions":0,"TallyArticles":0,"ShowAsTag":false,"IsPersonalised":false},{"Name":"TechNet Guru Contributions - May 2015 - TechNet Articles - United States (English) - TechNet Wiki","SafeName":"ronen ariely","TallyMentions":0,"TallyArticles":0,"ShowAsTag":false,"IsPersonalised":false},{"Name":"TechNet Guru Contributions - May 2015 - TechNet Articles - United States (English) - TechNet Wiki","SafeName":"rule","TallyMentions":0,"TallyArticles":0,"ShowAsTag":false,"IsPersonalised":false},{"Name":"TechNet Guru Contributions - May 2015 - TechNet Articles - United States (English) - TechNet Wiki","SafeName":"rules","TallyMentions":0,"TallyArticles":0,"ShowAsTag":false,"IsPersonalised":false},{"Name":"TechNet Guru Contributions - May 2015 - TechNet Articles - United States (English) - TechNet Wiki","SafeName":"s competition","TallyMentions":0,"TallyArticles":0,"ShowAsTag":false,"IsPersonalised":false},{"Name":"TechNet Guru Contributions - May 2015 - TechNet Articles - United States (English) - TechNet Wiki","SafeName":"s content","TallyMentions":0,"TallyArticles":0,"ShowAsTag":false,"IsPersonalised":false},{"Name":"TechNet Guru Contributions - May 2015 - TechNet Articles - United States (English) - TechNet Wiki","SafeName":"s forum announcements","TallyMentions":0,"TallyArticles":0,"ShowAsTag":false,"IsPersonalised":false},{"Name":"TechNet Guru Contributions - May 2015 - TechNet Articles - United States (English) - TechNet Wiki","SafeName":"saeid","TallyMentions":0,"TallyArticles":0,"ShowAsTag":false,"IsPersonalised":false},{"Name":"TechNet Guru Contributions - May 2015 - TechNet Articles - United States (English) - TechNet Wiki","SafeName":"sandro pereira biztalk server","TallyMentions":0,"TallyArticles":0,"ShowAsTag":false,"IsPersonalised":false},{"Name":"TechNet Guru Contributions - May 2015 - TechNet Articles - United States (English) - TechNet Wiki","SafeName":"santhosh sivarajan","TallyMentions":0,"TallyArticles":0,"ShowAsTag":false,"IsPersonalised":false},{"Name":"TechNet Guru Contributions - May 2015 - TechNet Articles - United States (English) - TechNet Wiki","SafeName":"scom","TallyMentions":0,"TallyArticles":0,"ShowAsTag":false,"IsPersonalised":false},{"Name":"TechNet Guru Contributions - May 2015 - TechNet Articles - United States (English) - TechNet Wiki","SafeName":"search service","TallyMentions":0,"TallyArticles":0,"ShowAsTag":false,"IsPersonalised":false},{"Name":"TechNet Guru Contributions - May 2015 - TechNet Articles - United States (English) - TechNet Wiki","SafeName":"sections","TallyMentions":0,"TallyArticles":0,"ShowAsTag":false,"IsPersonalised":false},{"Name":"TechNet Guru Contributions - May 2015 - TechNet Articles - United States (English) - TechNet Wiki","SafeName":"servers","TallyMentions":0,"TallyArticles":0,"ShowAsTag":false,"IsPersonalised":false},{"Name":"TechNet Guru Contributions - May 2015 - TechNet Articles - United States (English) - TechNet Wiki","SafeName":"singh jaggi sharepoint server","TallyMentions":0,"TallyArticles":0,"ShowAsTag":false,"IsPersonalised":false},{"Name":"TechNet Guru Contributions - May 2015 - TechNet Articles - United States (English) - TechNet Wiki","SafeName":"site collection","TallyMentions":0,"TallyArticles":0,"ShowAsTag":false,"IsPersonalised":false},{"Name":"TechNet Guru Contributions - May 2015 - TechNet Articles - United States (English) - TechNet Wiki","SafeName":"small basic contribution","TallyMentions":0,"TallyArticles":0,"ShowAsTag":false,"IsPersonalised":false},{"Name":"TechNet Guru Contributions - May 2015 - TechNet Articles - United States (English) - TechNet Wiki","SafeName":"small basic extension library","TallyMentions":0,"TallyArticles":0,"ShowAsTag":false,"IsPersonalised":false},{"Name":"TechNet Guru Contributions - May 2015 - TechNet Articles - United States (English) - TechNet Wiki","SafeName":"small basicsql bi","TallyMentions":0,"TallyArticles":0,"ShowAsTag":false,"IsPersonalised":false},{"Name":"TechNet Guru Contributions - May 2015 - TechNet Articles - United States (English) - TechNet Wiki","SafeName":"solutions","TallyMentions":0,"TallyArticles":0,"ShowAsTag":false,"IsPersonalised":false},{"Name":"TechNet Guru Contributions - May 2015 - TechNet Articles - United States (English) - TechNet Wiki","SafeName":"sort","TallyMentions":0,"TallyArticles":0,"ShowAsTag":false,"IsPersonalised":false},{"Name":"TechNet Guru Contributions - May 2015 - TechNet Articles - United States (English) - TechNet Wiki","SafeName":"sort data","TallyMentions":0,"TallyArticles":0,"ShowAsTag":false,"IsPersonalised":false},{"Name":"TechNet Guru Contributions - May 2015 - TechNet Articles - United States (English) - TechNet Wiki","SafeName":"specified object","TallyMentions":0,"TallyArticles":0,"ShowAsTag":false,"IsPersonalised":false},{"Name":"TechNet Guru Contributions - May 2015 - TechNet Articles - United States (English) - TechNet Wiki","SafeName":"splitview","TallyMentions":0,"TallyArticles":0,"ShowAsTag":false,"IsPersonalised":false},{"Name":"TechNet Guru Contributions - May 2015 - TechNet Articles - United States (English) - TechNet Wiki","SafeName":"sql agent job","TallyMentions":0,"TallyArticles":0,"ShowAsTag":false,"IsPersonalised":false},{"Name":"TechNet Guru Contributions - May 2015 - TechNet Articles - United States (English) - TechNet Wiki","SafeName":"sql bi","TallyMentions":0,"TallyArticles":0,"ShowAsTag":false,"IsPersonalised":false},{"Name":"TechNet Guru Contributions - May 2015 - TechNet Articles - United States (English) - TechNet Wiki","SafeName":"sql server","TallyMentions":0,"TallyArticles":0,"ShowAsTag":false,"IsPersonalised":false},{"Name":"TechNet Guru Contributions - May 2015 - TechNet Articles - United States (English) - TechNet Wiki","SafeName":"sql server contribution","TallyMentions":0,"TallyArticles":0,"ShowAsTag":false,"IsPersonalised":false},{"Name":"TechNet Guru Contributions - May 2015 - TechNet Articles - United States (English) - TechNet Wiki","SafeName":"sql server general","TallyMentions":0,"TallyArticles":0,"ShowAsTag":false,"IsPersonalised":false},{"Name":"TechNet Guru Contributions - May 2015 - TechNet Articles - United States (English) - TechNet Wiki","SafeName":"sridhar vishwanatham","TallyMentions":0,"TallyArticles":0,"ShowAsTag":false,"IsPersonalised":false},{"Name":"TechNet Guru Contributions - May 2015 - TechNet Articles - United States (English) - TechNet Wiki","SafeName":"ss dbe","TallyMentions":0,"TallyArticles":0,"ShowAsTag":false,"IsPersonalised":false},{"Name":"TechNet Guru Contributions - May 2015 - TechNet Articles - United States (English) - TechNet Wiki","SafeName":"steps","TallyMentions":0,"TallyArticles":0,"ShowAsTag":false,"IsPersonalised":false},{"Name":"TechNet Guru Contributions - May 2015 - TechNet Articles - United States (English) - TechNet Wiki","SafeName":"store app","TallyMentions":0,"TallyArticles":0,"ShowAsTag":false,"IsPersonalised":false},{"Name":"TechNet Guru Contributions - May 2015 - TechNet Articles - United States (English) - TechNet Wiki","SafeName":"store coordinates","TallyMentions":0,"TallyArticles":0,"ShowAsTag":false,"IsPersonalised":false},{"Name":"TechNet Guru Contributions - May 2015 - TechNet Articles - United States (English) - TechNet Wiki","SafeName":"subject matter experts","TallyMentions":0,"TallyArticles":0,"ShowAsTag":false,"IsPersonalised":false},{"Name":"TechNet Guru Contributions - May 2015 - TechNet Articles - United States (English) - TechNet Wiki","SafeName":"sumantro","TallyMentions":0,"TallyArticles":0,"ShowAsTag":false,"IsPersonalised":false},{"Name":"TechNet Guru Contributions - May 2015 - TechNet Articles - United States (English) - TechNet Wiki","SafeName":"sumantro localization","TallyMentions":0,"TallyArticles":0,"ShowAsTag":false,"IsPersonalised":false},{"Name":"TechNet Guru Contributions - May 2015 - TechNet Articles - United States (English) - TechNet Wiki","SafeName":"synonym","TallyMentions":0,"TallyArticles":0,"ShowAsTag":false,"IsPersonalised":false},{"Name":"TechNet Guru Contributions - May 2015 - TechNet Articles - United States (English) - TechNet Wiki","SafeName":"system center","TallyMentions":0,"TallyArticles":0,"ShowAsTag":false,"IsPersonalised":false},{"Name":"TechNet Guru Contributions - May 2015 - TechNet Articles - United States (English) - TechNet Wiki","SafeName":"system center contribution","TallyMentions":0,"TallyArticles":0,"ShowAsTag":false,"IsPersonalised":false},{"Name":"TechNet Guru Contributions - May 2015 - TechNet Articles - United States (English) - TechNet Wiki","SafeName":"t necessary","TallyMentions":0,"TallyArticles":0,"ShowAsTag":false,"IsPersonalised":false},{"Name":"TechNet Guru Contributions - May 2015 - TechNet Articles - United States (English) - TechNet Wiki","SafeName":"tab","TallyMentions":0,"TallyArticles":0,"ShowAsTag":false,"IsPersonalised":false},{"Name":"TechNet Guru Contributions - May 2015 - TechNet Articles - United States (English) - TechNet Wiki","SafeName":"takahashi small basic","TallyMentions":0,"TallyArticles":0,"ShowAsTag":false,"IsPersonalised":false},{"Name":"TechNet Guru Contributions - May 2015 - TechNet Articles - United States (English) - TechNet Wiki","SafeName":"technet forum solutions","TallyMentions":0,"TallyArticles":0,"ShowAsTag":false,"IsPersonalised":false},{"Name":"TechNet Guru Contributions - May 2015 - TechNet Articles - United States (English) - TechNet Wiki","SafeName":"technet forums","TallyMentions":0,"TallyArticles":0,"ShowAsTag":false,"IsPersonalised":false},{"Name":"TechNet Guru Contributions - May 2015 - TechNet Articles - United States (English) - TechNet Wiki","SafeName":"technet guru competition","TallyMentions":0,"TallyArticles":0,"ShowAsTag":false,"IsPersonalised":false},{"Name":"TechNet Guru Contributions - May 2015 - TechNet Articles - United States (English) - TechNet Wiki","SafeName":"technet guru contributions","TallyMentions":0,"TallyArticles":0,"ShowAsTag":false,"IsPersonalised":false},{"Name":"TechNet Guru Contributions - May 2015 - TechNet Articles - United States (English) - TechNet Wiki","SafeName":"technet ninjas","TallyMentions":0,"TallyArticles":0,"ShowAsTag":false,"IsPersonalised":false},{"Name":"TechNet Guru Contributions - May 2015 - TechNet Articles - United States (English) - TechNet Wiki","SafeName":"technet wiki","TallyMentions":0,"TallyArticles":0,"ShowAsTag":false,"IsPersonalised":false},{"Name":"TechNet Guru Contributions - May 2015 - TechNet Articles - United States (English) - TechNet Wiki","SafeName":"technet wiki article","TallyMentions":0,"TallyArticles":0,"ShowAsTag":false,"IsPersonalised":false},{"Name":"TechNet Guru Contributions - May 2015 - TechNet Articles - United States (English) - TechNet Wiki","SafeName":"technet wiki articles","TallyMentions":0,"TallyArticles":0,"ShowAsTag":false,"IsPersonalised":false},{"Name":"TechNet Guru Contributions - May 2015 - TechNet Articles - United States (English) - TechNet Wiki","SafeName":"technet wiki awards program","TallyMentions":0,"TallyArticles":0,"ShowAsTag":false,"IsPersonalised":false},{"Name":"TechNet Guru Contributions - May 2015 - TechNet Articles - United States (English) - TechNet Wiki","SafeName":"technet wiki guru competition","TallyMentions":0,"TallyArticles":0,"ShowAsTag":false,"IsPersonalised":false},{"Name":"TechNet Guru Contributions - May 2015 - TechNet Articles - United States (English) - TechNet Wiki","SafeName":"technet wiki page","TallyMentions":0,"TallyArticles":0,"ShowAsTag":false,"IsPersonalised":false},{"Name":"TechNet Guru Contributions - May 2015 - TechNet Articles - United States (English) - TechNet Wiki","SafeName":"technologies","TallyMentions":0,"TallyArticles":0,"ShowAsTag":false,"IsPersonalised":false},{"Name":"TechNet Guru Contributions - May 2015 - TechNet Articles - United States (English) - TechNet Wiki","SafeName":"temperature","TallyMentions":0,"TallyArticles":0,"ShowAsTag":false,"IsPersonalised":false},{"Name":"TechNet Guru Contributions - May 2015 - TechNet Articles - United States (English) - TechNet Wiki","SafeName":"tn wiki","TallyMentions":0,"TallyArticles":0,"ShowAsTag":false,"IsPersonalised":false},{"Name":"TechNet Guru Contributions - May 2015 - TechNet Articles - United States (English) - TechNet Wiki","SafeName":"tom mohan","TallyMentions":0,"TallyArticles":0,"ShowAsTag":false,"IsPersonalised":false},{"Name":"TechNet Guru Contributions - May 2015 - TechNet Articles - United States (English) - TechNet Wiki","SafeName":"tommytwotrain","TallyMentions":0,"TallyArticles":0,"ShowAsTag":false,"IsPersonalised":false},{"Name":"TechNet Guru Contributions - May 2015 - TechNet Articles - United States (English) - TechNet Wiki","SafeName":"trackevent","TallyMentions":0,"TallyArticles":0,"ShowAsTag":false,"IsPersonalised":false},{"Name":"TechNet Guru Contributions - May 2015 - TechNet Articles - United States (English) - TechNet Wiki","SafeName":"trigger","TallyMentions":0,"TallyArticles":0,"ShowAsTag":false,"IsPersonalised":false},{"Name":"TechNet Guru Contributions - May 2015 - TechNet Articles - United States (English) - TechNet Wiki","SafeName":"t-sql","TallyMentions":0,"TallyArticles":0,"ShowAsTag":false,"IsPersonalised":false},{"Name":"TechNet Guru Contributions - May 2015 - TechNet Articles - United States (English) - TechNet Wiki","SafeName":"t-sql contribution","TallyMentions":0,"TallyArticles":0,"ShowAsTag":false,"IsPersonalised":false},{"Name":"TechNet Guru Contributions - May 2015 - TechNet Articles - United States (English) - TechNet Wiki","SafeName":"tweet","TallyMentions":0,"TallyArticles":0,"ShowAsTag":false,"IsPersonalised":false},{"Name":"TechNet Guru Contributions - May 2015 - TechNet Articles - United States (English) - TechNet Wiki","SafeName":"ui","TallyMentions":0,"TallyArticles":0,"ShowAsTag":false,"IsPersonalised":false},{"Name":"TechNet Guru Contributions - May 2015 - TechNet Articles - United States (English) - TechNet Wiki","SafeName":"universal app dev","TallyMentions":0,"TallyArticles":0,"ShowAsTag":false,"IsPersonalised":false},{"Name":"TechNet Guru Contributions - May 2015 - TechNet Articles - United States (English) - TechNet Wiki","SafeName":"universal windows apps","TallyMentions":0,"TallyArticles":0,"ShowAsTag":false,"IsPersonalised":false},{"Name":"TechNet Guru Contributions - May 2015 - TechNet Articles - United States (English) - TechNet Wiki","SafeName":"url","TallyMentions":0,"TallyArticles":0,"ShowAsTag":false,"IsPersonalised":false},{"Name":"TechNet Guru Contributions - May 2015 - TechNet Articles - United States (English) - TechNet Wiki","SafeName":"useful powershell commands","TallyMentions":0,"TallyArticles":0,"ShowAsTag":false,"IsPersonalised":false},{"Name":"TechNet Guru Contributions - May 2015 - TechNet Articles - United States (English) - TechNet Wiki","SafeName":"vb contribution","TallyMentions":0,"TallyArticles":0,"ShowAsTag":false,"IsPersonalised":false},{"Name":"TechNet Guru Contributions - May 2015 - TechNet Articles - United States (English) - TechNet Wiki","SafeName":"vbnet","TallyMentions":0,"TallyArticles":0,"ShowAsTag":false,"IsPersonalised":false},{"Name":"TechNet Guru Contributions - May 2015 - TechNet Articles - United States (English) - TechNet Wiki","SafeName":"viewmodel","TallyMentions":0,"TallyArticles":0,"ShowAsTag":false,"IsPersonalised":false},{"Name":"TechNet Guru Contributions - May 2015 - TechNet Articles - United States (English) - TechNet Wiki","SafeName":"visual c#","TallyMentions":0,"TallyArticles":0,"ShowAsTag":false,"IsPersonalised":false},{"Name":"TechNet Guru Contributions - May 2015 - TechNet Articles - United States (English) - TechNet Wiki","SafeName":"vsserror","TallyMentions":0,"TallyArticles":0,"ShowAsTag":false,"IsPersonalised":false},{"Name":"TechNet Guru Contributions - May 2015 - TechNet Articles - United States (English) - TechNet Wiki","SafeName":"wcf","TallyMentions":0,"TallyArticles":0,"ShowAsTag":false,"IsPersonalised":false},{"Name":"TechNet Guru Contributions - May 2015 - TechNet Articles - United States (English) - TechNet Wiki","SafeName":"web application","TallyMentions":0,"TallyArticles":0,"ShowAsTag":false,"IsPersonalised":false},{"Name":"TechNet Guru Contributions - May 2015 - TechNet Articles - United States (English) - TechNet Wiki","SafeName":"webserver","TallyMentions":0,"TallyArticles":0,"ShowAsTag":false,"IsPersonalised":false},{"Name":"TechNet Guru Contributions - May 2015 - TechNet Articles - United States (English) - TechNet Wiki","SafeName":"wiki article","TallyMentions":0,"TallyArticles":0,"ShowAsTag":false,"IsPersonalised":false},{"Name":"TechNet Guru Contributions - May 2015 - TechNet Articles - United States (English) - TechNet Wiki","SafeName":"wiki links","TallyMentions":0,"TallyArticles":0,"ShowAsTag":false,"IsPersonalised":false},{"Name":"TechNet Guru Contributions - May 2015 - TechNet Articles - United States (English) - TechNet Wiki","SafeName":"wiki ninjas blog","TallyMentions":0,"TallyArticles":0,"ShowAsTag":false,"IsPersonalised":false},{"Name":"TechNet Guru Contributions - May 2015 - TechNet Articles - United States (English) - TechNet Wiki","SafeName":"wiki ninjas twitter","TallyMentions":0,"TallyArticles":0,"ShowAsTag":false,"IsPersonalised":false},{"Name":"TechNet Guru Contributions - May 2015 - TechNet Articles - United States (English) - TechNet Wiki","SafeName":"windows","TallyMentions":0,"TallyArticles":0,"ShowAsTag":false,"IsPersonalised":false},{"Name":"TechNet Guru Contributions - May 2015 - TechNet Articles - United States (English) - TechNet Wiki","SafeName":"windows phone","TallyMentions":0,"TallyArticles":0,"ShowAsTag":false,"IsPersonalised":false},{"Name":"TechNet Guru Contributions - May 2015 - TechNet Articles - United States (English) - TechNet Wiki","SafeName":"windows phone contribution","TallyMentions":0,"TallyArticles":0,"ShowAsTag":false,"IsPersonalised":false},{"Name":"TechNet Guru Contributions - May 2015 - TechNet Articles - United States (English) - TechNet Wiki","SafeName":"windows powershell","TallyMentions":0,"TallyArticles":0,"ShowAsTag":false,"IsPersonalised":false},{"Name":"TechNet Guru Contributions - May 2015 - TechNet Articles - United States (English) - TechNet Wiki","SafeName":"windows server","TallyMentions":0,"TallyArticles":0,"ShowAsTag":false,"IsPersonalised":false},{"Name":"TechNet Guru Contributions - May 2015 - TechNet Articles - United States (English) - TechNet Wiki","SafeName":"windows serverwiki","TallyMentions":0,"TallyArticles":0,"ShowAsTag":false,"IsPersonalised":false},{"Name":"TechNet Guru Contributions - May 2015 - TechNet Articles - United States (English) - TechNet Wiki","SafeName":"windows service","TallyMentions":0,"TallyArticles":0,"ShowAsTag":false,"IsPersonalised":false},{"Name":"TechNet Guru Contributions - May 2015 - TechNet Articles - United States (English) - TechNet Wiki","SafeName":"windows store","TallyMentions":0,"TallyArticles":0,"ShowAsTag":false,"IsPersonalised":false},{"Name":"TechNet Guru Contributions - May 2015 - TechNet Articles - United States (English) - TechNet Wiki","SafeName":"windows universal apps","TallyMentions":0,"TallyArticles":0,"ShowAsTag":false,"IsPersonalised":false},{"Name":"TechNet Guru Contributions - May 2015 - TechNet Articles - United States (English) - TechNet Wiki","SafeName":"winners","TallyMentions":0,"TallyArticles":0,"ShowAsTag":false,"IsPersonalised":false},{"Name":"TechNet Guru Contributions - May 2015 - TechNet Articles - United States (English) - TechNet Wiki","SafeName":"winrt apps","TallyMentions":0,"TallyArticles":0,"ShowAsTag":false,"IsPersonalised":false},{"Name":"TechNet Guru Contributions - May 2015 - TechNet Articles - United States (English) - TechNet Wiki","SafeName":"wpf","TallyMentions":0,"TallyArticles":0,"ShowAsTag":false,"IsPersonalised":false},{"Name":"TechNet Guru Contributions - May 2015 - TechNet Articles - United States (English) - TechNet Wiki","SafeName":"wpf contribution","TallyMentions":0,"TallyArticles":0,"ShowAsTag":false,"IsPersonalised":false},{"Name":"TechNet Guru Contributions - May 2015 - TechNet Articles - United States (English) - TechNet Wiki","SafeName":"yan grenier","TallyMentions":0,"TallyArticles":0,"ShowAsTag":false,"IsPersonalised":false}],"Netities":[{"Name":"Table of contents","WikipediaUrl":null,"BingId":null,"Type":null,"SubType":null},{"Name":"Microsoft","WikipediaUrl":null,"BingId":null,"Type":"Organization","SubType":null},{"Name":"Identity column","WikipediaUrl":null,"BingId":null,"Type":null,"SubType":null},{"Name":"2010","WikipediaUrl":null,"BingId":null,"Type":"DateTime","SubType":"DateRange"},{"Name":"BasicSQL BI & Power BISQL Server General & Database","WikipediaUrl":null,"BingId":null,"Type":"Organization","SubType":null},{"Name":"Business intelligence","WikipediaUrl":null,"BingId":null,"Type":null,"SubType":null},{"Name":"Power Architecture","WikipediaUrl":null,"BingId":null,"Type":null,"SubType":null},{"Name":"Server (computing)","WikipediaUrl":null,"BingId":null,"Type":null,"SubType":null},{"Name":"Elemental Games","WikipediaUrl":null,"BingId":null,"Type":null,"SubType":null},{"Name":"Database","WikipediaUrl":null,"BingId":null,"Type":null,"SubType":null},{"Name":"Microsoft Windows","WikipediaUrl":null,"BingId":null,"Type":null,"SubType":null},{"Name":"Corel Presentations","WikipediaUrl":null,"BingId":null,"Type":null,"SubType":null},{"Name":"Foundation (framework)","WikipediaUrl":null,"BingId":null,"Type":null,"SubType":null},{"Name":"Windows Presentation Foundation","WikipediaUrl":null,"BingId":null,"Type":null,"SubType":null},{"Name":"Se","WikipediaUrl":null,"BingId":null,"Type":null,"SubType":null},{"Name":"Internet forum","WikipediaUrl":null,"BingId":null,"Type":null,"SubType":null},{"Name":"May","WikipediaUrl":null,"BingId":null,"Type":"DateTime","SubType":"DateRange"},{"Name":"Introduction (writing)","WikipediaUrl":null,"BingId":null,"Type":null,"SubType":null},{"Name":"now","WikipediaUrl":null,"BingId":null,"Type":"DateTime","SubType":null},{"Name":"June","WikipediaUrl":null,"BingId":null,"Type":"DateTime","SubType":"DateRange"},{"Name":"- 8","WikipediaUrl":null,"BingId":null,"Type":"Quantity","SubType":"Number"},{"Name":"If You","WikipediaUrl":null,"BingId":null,"Type":null,"SubType":null},{"Name":"Blog","WikipediaUrl":null,"BingId":null,"Type":null,"SubType":null},{"Name":"Microsoft TechNet","WikipediaUrl":null,"BingId":null,"Type":null,"SubType":null},{"Name":"Wiki","WikipediaUrl":null,"BingId":null,"Type":null,"SubType":null},{"Name":"us","WikipediaUrl":null,"BingId":null,"Type":"Location","SubType":null},{"Name":"THIS IS","WikipediaUrl":null,"BingId":null,"Type":null,"SubType":null},{"Name":"MAY","WikipediaUrl":null,"BingId":null,"Type":"DateTime","SubType":"DateRange"},{"Name":"Hyperlink","WikipediaUrl":null,"BingId":null,"Type":null,"SubType":null},{"Name":"One","WikipediaUrl":null,"BingId":null,"Type":"Quantity","SubType":"Number"},{"Name":"each month","WikipediaUrl":null,"BingId":null,"Type":"DateTime","SubType":"Set"},{"Name":"MSDN/TechNet Ninjas","WikipediaUrl":null,"BingId":null,"Type":"Organization","SubType":null},{"Name":"Microsoft Developer Network","WikipediaUrl":null,"BingId":null,"Type":null,"SubType":null},{"Name":"Microsoft TechNet","WikipediaUrl":null,"BingId":null,"Type":null,"SubType":null},{"Name":"Wikipedia","WikipediaUrl":null,"BingId":null,"Type":null,"SubType":null},{"Name":"Twitter","WikipediaUrl":null,"BingId":null,"Type":null,"SubType":null},{"Name":"Winners","WikipediaUrl":null,"BingId":null,"Type":null,"SubType":null},{"Name":"five","WikipediaUrl":null,"BingId":null,"Type":"Quantity","SubType":"Number"},{"Name":"3","WikipediaUrl":null,"BingId":null,"Type":"Quantity","SubType":"Number"},{"Name":"TechNet Wiki Community Council","WikipediaUrl":null,"BingId":null,"Type":"Organization","SubType":null},{"Name":"Community councils of Lesotho","WikipediaUrl":null,"BingId":null,"Type":null,"SubType":null},{"Name":"2","WikipediaUrl":null,"BingId":null,"Type":"Quantity","SubType":"Number"},{"Name":"Microsoft Employee SMEs (Subject Matter Experts","WikipediaUrl":null,"BingId":null,"Type":"Organization","SubType":null},{"Name":"Microsoft","WikipediaUrl":null,"BingId":null,"Type":null,"SubType":null},{"Name":"Employment","WikipediaUrl":null,"BingId":null,"Type":null,"SubType":null},{"Name":"Subject-matter expert","WikipediaUrl":null,"BingId":null,"Type":null,"SubType":null},{"Name":"May 2015","WikipediaUrl":null,"BingId":null,"Type":"DateTime","SubType":"DateRange"},{"Name":"English language","WikipediaUrl":null,"BingId":null,"Type":null,"SubType":null},{"Name":"before May","WikipediaUrl":null,"BingId":null,"Type":"DateTime","SubType":"DateRange"},{"Name":"Wikipedia","WikipediaUrl":null,"BingId":null,"Type":null,"SubType":null},{"Name":"1","WikipediaUrl":null,"BingId":null,"Type":"Quantity","SubType":"Number"},{"Name":"How-to","WikipediaUrl":null,"BingId":null,"Type":null,"SubType":null},{"Name":"Enter key","WikipediaUrl":null,"BingId":null,"Type":null,"SubType":null},{"Name":"Microsoft TechNet","WikipediaUrl":null,"BingId":null,"Type":null,"SubType":null},{"Name":"Copyright","WikipediaUrl":null,"BingId":null,"Type":null,"SubType":null},{"Name":"You","WikipediaUrl":null,"BingId":null,"Type":null,"SubType":null},{"Name":"FromSoftware","WikipediaUrl":null,"BingId":null,"Type":null,"SubType":null},{"Name":"Microsoft Developer Network","WikipediaUrl":null,"BingId":null,"Type":null,"SubType":null},{"Name":"Internet forum","WikipediaUrl":null,"BingId":null,"Type":null,"SubType":null},{"Name":"Over (cricket)","WikipediaUrl":null,"BingId":null,"Type":null,"SubType":null},{"Name":"MAY","WikipediaUrl":null,"BingId":null,"Type":"DateTime","SubType":"DateRange"},{"Name":".to","WikipediaUrl":null,"BingId":null,"Type":null,"SubType":null},{"Name":"Wiki","WikipediaUrl":null,"BingId":null,"Type":null,"SubType":null},{"Name":"India","WikipediaUrl":null,"BingId":null,"Type":null,"SubType":null},{"Name":"Award","WikipediaUrl":null,"BingId":null,"Type":null,"SubType":null},{"Name":"Login","WikipediaUrl":null,"BingId":null,"Type":null,"SubType":null},{"Name":"Microsoft","WikipediaUrl":null,"BingId":null,"Type":"Organization","SubType":null},{"Name":"Addition","WikipediaUrl":null,"BingId":null,"Type":null,"SubType":null},{"Name":"http://social.technet.microsoft.com/wiki/contents/articles/add.aspx%20","WikipediaUrl":null,"BingId":null,"Type":"URL","SubType":null},{"Name":"20","WikipediaUrl":null,"BingId":null,"Type":"Quantity","SubType":"Number"},{"Name":"If You","WikipediaUrl":null,"BingId":null,"Type":null,"SubType":null},{"Name":"Microsoft Developer Network","WikipediaUrl":null,"BingId":null,"Type":null,"SubType":null},{"Name":"Microsoft TechNet","WikipediaUrl":null,"BingId":null,"Type":null,"SubType":null},{"Name":"Wiki","WikipediaUrl":null,"BingId":null,"Type":null,"SubType":null},{"Name":"2","WikipediaUrl":null,"BingId":null,"Type":"Quantity","SubType":"Number"},{"Name":"us","WikipediaUrl":null,"BingId":null,"Type":"Location","SubType":null},{"Name":"Tell (archaeology)","WikipediaUrl":null,"BingId":null,"Type":null,"SubType":null},{"Name":".to","WikipediaUrl":null,"BingId":null,"Type":null,"SubType":null},{"Name":"Login","WikipediaUrl":null,"BingId":null,"Type":null,"SubType":null},{"Name":"Microsoft","WikipediaUrl":null,"BingId":null,"Type":"Organization","SubType":null},{"Name":"Point and click","WikipediaUrl":null,"BingId":null,"Type":null,"SubType":null},{"Name":"URL","WikipediaUrl":null,"BingId":null,"Type":null,"SubType":null},{"Name":"Category (mathematics)","WikipediaUrl":null,"BingId":null,"Type":null,"SubType":null},{"Name":"MAY","WikipediaUrl":null,"BingId":null,"Type":"DateTime","SubType":"DateRange"},{"Name":"Fundraising","WikipediaUrl":null,"BingId":null,"Type":null,"SubType":null},{"Name":"Below (video game)","WikipediaUrl":null,"BingId":null,"Type":null,"SubType":null},{"Name":"IBM Notes","WikipediaUrl":null,"BingId":null,"Type":null,"SubType":null},{"Name":"MAY 2015","WikipediaUrl":null,"BingId":null,"Type":"DateTime","SubType":"DateRange"},{"Name":"Microsoft Azure\r\nThe TechNet Guru","WikipediaUrl":null,"BingId":null,"Type":"Organization","SubType":null},{"Name":"Microsoft Azure","WikipediaUrl":null,"BingId":null,"Type":null,"SubType":null},{"Name":"Generic top-level domain","WikipediaUrl":null,"BingId":null,"Type":null,"SubType":null},{"Name":"POST (HTTP)","WikipediaUrl":null,"BingId":null,"Type":null,"SubType":null},{"Name":"Big Data Analytics","WikipediaUrl":null,"BingId":null,"Type":"Organization","SubType":null},{"Name":"Big data","WikipediaUrl":null,"BingId":null,"Type":null,"SubType":null},{"Name":"Chervine Azure PowerShell","WikipediaUrl":null,"BingId":null,"Type":"Organization","SubType":null},{"Name":"Microsoft Azure","WikipediaUrl":null,"BingId":null,"Type":null,"SubType":null},{"Name":"PowerShell","WikipediaUrl":null,"BingId":null,"Type":null,"SubType":null},{"Name":"Ken Cenerelli Custom Telemetry","WikipediaUrl":null,"BingId":null,"Type":"Organization","SubType":null},{"Name":"Modding","WikipediaUrl":null,"BingId":null,"Type":null,"SubType":null},{"Name":"Telemetry","WikipediaUrl":null,"BingId":null,"Type":null,"SubType":null},{"Name":"Event-driven programming","WikipediaUrl":null,"BingId":null,"Type":null,"SubType":null},{"Name":"Microsoft Application Insights","WikipediaUrl":null,"BingId":null,"Type":"Organization","SubType":null},{"Name":"Microsoft","WikipediaUrl":null,"BingId":null,"Type":null,"SubType":null},{"Name":"Application software","WikipediaUrl":null,"BingId":null,"Type":null,"SubType":null},{"Name":"Ken Cenerelli","WikipediaUrl":null,"BingId":null,"Type":"Person","SubType":null},{"Name":"Creation Ministries International","WikipediaUrl":null,"BingId":null,"Type":null,"SubType":null},{"Name":"Virtual machine","WikipediaUrl":null,"BingId":null,"Type":null,"SubType":null},{"Name":"Pooja Baraskar\r\nAzure Service","WikipediaUrl":null,"BingId":null,"Type":"Organization","SubType":null},{"Name":"Web service","WikipediaUrl":null,"BingId":null,"Type":null,"SubType":null},{"Name":"Santhosh Sivarajan","WikipediaUrl":null,"BingId":null,"Type":"Person","SubType":null},{"Name":"Web portal","WikipediaUrl":null,"BingId":null,"Type":null,"SubType":null},{"Name":"Guru","WikipediaUrl":null,"BingId":null,"Type":"Location","SubType":null},{"Name":"Generic top-level domain","WikipediaUrl":null,"BingId":null,"Type":null,"SubType":null},{"Name":".post","WikipediaUrl":null,"BingId":null,"Type":null,"SubType":null},{"Name":"Wiki","WikipediaUrl":null,"BingId":null,"Type":null,"SubType":null},{"Name":"Microsoft BizTalk Server","WikipediaUrl":null,"BingId":null,"Type":null,"SubType":null},{"Name":"WCF-SAP Adapter Step-by-Step Installation Guide","WikipediaUrl":null,"BingId":null,"Type":"Organization","SubType":null},{"Name":"Windows Server 2008 R2","WikipediaUrl":null,"BingId":null,"Type":null,"SubType":null},{"Name":"Windows Communication Foundation","WikipediaUrl":null,"BingId":null,"Type":null,"SubType":null},{"Name":"SAP SE","WikipediaUrl":null,"BingId":null,"Type":null,"SubType":null},{"Name":"Adapter","WikipediaUrl":null,"BingId":null,"Type":null,"SubType":null},{"Name":"Step by Step (TV series)","WikipediaUrl":null,"BingId":null,"Type":null,"SubType":null},{"Name":"Installation (computer programs)","WikipediaUrl":null,"BingId":null,"Type":null,"SubType":null},{"Name":"Guide (hypertext)","WikipediaUrl":null,"BingId":null,"Type":null,"SubType":null},{"Name":"Pereira, Colombia","WikipediaUrl":null,"BingId":null,"Type":null,"SubType":null},{"Name":"BizTalk Health Monitor","WikipediaUrl":null,"BingId":null,"Type":"Organization","SubType":null},{"Name":"How-to","WikipediaUrl":null,"BingId":null,"Type":null,"SubType":null},{"Name":"Health care","WikipediaUrl":null,"BingId":null,"Type":null,"SubType":null},{"Name":"Computer monitor","WikipediaUrl":null,"BingId":null,"Type":null,"SubType":null},{"Name":"one","WikipediaUrl":null,"BingId":null,"Type":"Quantity","SubType":"Number"},{"Name":"Sandro Pereira","WikipediaUrl":null,"BingId":null,"Type":"Organization","SubType":null},{"Name":"BizTalk","WikipediaUrl":null,"BingId":null,"Type":"Organization","SubType":null},{"Name":"DevOps","WikipediaUrl":null,"BingId":null,"Type":null,"SubType":null},{"Name":"Sandro\r\n Pereira","WikipediaUrl":null,"BingId":null,"Type":"Organization","SubType":null},{"Name":"Track and field","WikipediaUrl":null,"BingId":null,"Type":null,"SubType":null},{"Name":"The Same Computer","WikipediaUrl":null,"BingId":null,"Type":"Organization","SubType":null},{"Name":"Johns-305 \r\nForefront Identity","WikipediaUrl":null,"BingId":null,"Type":"Organization","SubType":null},{"Name":"Cross compiler","WikipediaUrl":null,"BingId":null,"Type":null,"SubType":null},{"Name":"-305","WikipediaUrl":null,"BingId":null,"Type":"Quantity","SubType":"Number"},{"Name":"Ontario","WikipediaUrl":null,"BingId":null,"Type":null,"SubType":null},{"Name":"The Same","WikipediaUrl":null,"BingId":null,"Type":null,"SubType":null},{"Name":"Personal computer","WikipediaUrl":null,"BingId":null,"Type":null,"SubType":null},{"Name":"TechNet Guru","WikipediaUrl":null,"BingId":null,"Type":"Organization","SubType":null},{"Name":"Forefront Identity Manager","WikipediaUrl":null,"BingId":null,"Type":null,"SubType":null},{"Name":"Microsoft TechNet","WikipediaUrl":null,"BingId":null,"Type":null,"SubType":null},{"Name":"Wiki","WikipediaUrl":null,"BingId":null,"Type":null,"SubType":null},{"Name":"FIM","WikipediaUrl":null,"BingId":null,"Type":"Quantity","SubType":"Currency"},{"Name":"2010","WikipediaUrl":null,"BingId":null,"Type":"DateTime","SubType":"DateRange"},{"Name":"2013","WikipediaUrl":null,"BingId":null,"Type":"DateTime","SubType":"DateRange"},{"Name":"SharePoint","WikipediaUrl":null,"BingId":null,"Type":null,"SubType":null},{"Name":"Guru","WikipediaUrl":null,"BingId":null,"Type":"Location","SubType":null},{"Name":"Generic top-level domain","WikipediaUrl":null,"BingId":null,"Type":null,"SubType":null},{"Name":".post","WikipediaUrl":null,"BingId":null,"Type":null,"SubType":null},{"Name":"Oracle Database","WikipediaUrl":null,"BingId":null,"Type":"Organization","SubType":null},{"Name":"List (abstract data type)","WikipediaUrl":null,"BingId":null,"Type":null,"SubType":null},{"Name":"Dan Christian\r\nWhat","WikipediaUrl":null,"BingId":null,"Type":"Person","SubType":null},{"Name":"Web application","WikipediaUrl":null,"BingId":null,"Type":null,"SubType":null},{"Name":"Inderjeet\r\n Singh","WikipediaUrl":null,"BingId":null,"Type":"Person","SubType":null},{"Name":"Singh","WikipediaUrl":null,"BingId":null,"Type":"Person","SubType":null},{"Name":"WhatsApp","WikipediaUrl":null,"BingId":null,"Type":null,"SubType":null},{"Name":"Farm","WikipediaUrl":null,"BingId":null,"Type":null,"SubType":null},{"Name":"A-site","WikipediaUrl":null,"BingId":null,"Type":null,"SubType":null},{"Name":"Collection (artwork)","WikipediaUrl":null,"BingId":null,"Type":null,"SubType":null},{"Name":"2016","WikipediaUrl":null,"BingId":null,"Type":"DateTime","SubType":"DateRange"},{"Name":"Inderjeet\r\n Singh Jaggi Excel Services","WikipediaUrl":null,"BingId":null,"Type":"Organization","SubType":null},{"Name":"Excel Services","WikipediaUrl":null,"BingId":null,"Type":null,"SubType":null},{"Name":"2013","WikipediaUrl":null,"BingId":null,"Type":"DateTime","SubType":"DateRange"},{"Name":"2010","WikipediaUrl":null,"BingId":null,"Type":"DateTime","SubType":"DateRange"},{"Name":"Denmark","WikipediaUrl":null,"BingId":null,"Type":null,"SubType":null},{"Name":"Islam","WikipediaUrl":null,"BingId":null,"Type":null,"SubType":null},{"Name":"Working class","WikipediaUrl":null,"BingId":null,"Type":null,"SubType":null},{"Name":"Custom List Forms","WikipediaUrl":null,"BingId":null,"Type":"Organization","SubType":null},{"Name":"Social norm","WikipediaUrl":null,"BingId":null,"Type":null,"SubType":null},{"Name":"List (abstract data type)","WikipediaUrl":null,"BingId":null,"Type":null,"SubType":null},{"Name":"Islam \r\nSmall Basic\r\nThe TechNet Guru","WikipediaUrl":null,"BingId":null,"Type":"Organization","SubType":null},{"Name":"Microsoft Small Basic","WikipediaUrl":null,"BingId":null,"Type":null,"SubType":null},{"Name":"Generic top-level domain","WikipediaUrl":null,"BingId":null,"Type":null,"SubType":null},{"Name":"POST (HTTP)","WikipediaUrl":null,"BingId":null,"Type":null,"SubType":null},{"Name":"Wiki","WikipediaUrl":null,"BingId":null,"Type":null,"SubType":null},{"Name":"Kinect","WikipediaUrl":null,"BingId":null,"Type":null,"SubType":null},{"Name":"BASIC extension","WikipediaUrl":null,"BingId":null,"Type":null,"SubType":null},{"Name":"Nonki\r\n Takahashi","WikipediaUrl":null,"BingId":null,"Type":"Organization","SubType":null},{"Name":"SQL BI & Power BI \r\nThe TechNet Guru","WikipediaUrl":null,"BingId":null,"Type":"Organization","SubType":null},{"Name":"SQL","WikipediaUrl":null,"BingId":null,"Type":null,"SubType":null},{"Name":"Business intelligence","WikipediaUrl":null,"BingId":null,"Type":null,"SubType":null},{"Name":"Power BI","WikipediaUrl":null,"BingId":null,"Type":null,"SubType":null},{"Name":"BI","WikipediaUrl":null,"BingId":null,"Type":"Organization","SubType":null},{"Name":"SQL Server General & Database Engine\r\nThe TechNet Guru","WikipediaUrl":null,"BingId":null,"Type":"Organization","SubType":null},{"Name":"Microsoft SQL Server","WikipediaUrl":null,"BingId":null,"Type":null,"SubType":null},{"Name":"Database engine","WikipediaUrl":null,"BingId":null,"Type":null,"SubType":null},{"Name":"Developer Friendly XML Extraction From SQL Server by\r\n\r\nAndy ONeill \r\nSystem Center\r\nThe TechNet Guru","WikipediaUrl":null,"BingId":null,"Type":"Organization","SubType":null},{"Name":"Programmer","WikipediaUrl":null,"BingId":null,"Type":null,"SubType":null},{"Name":"XML","WikipediaUrl":null,"BingId":null,"Type":null,"SubType":null},{"Name":"Microsoft SQL Server","WikipediaUrl":null,"BingId":null,"Type":null,"SubType":null},{"Name":"Operating system","WikipediaUrl":null,"BingId":null,"Type":null,"SubType":null},{"Name":"Center (group theory)","WikipediaUrl":null,"BingId":null,"Type":null,"SubType":null},{"Name":"Generic top-level domain","WikipediaUrl":null,"BingId":null,"Type":null,"SubType":null},{"Name":"POST (HTTP)","WikipediaUrl":null,"BingId":null,"Type":null,"SubType":null},{"Name":"System Center","WikipediaUrl":null,"BingId":null,"Type":"Organization","SubType":null},{"Name":"Wiki","WikipediaUrl":null,"BingId":null,"Type":null,"SubType":null},{"Name":"30111","WikipediaUrl":null,"BingId":null,"Type":"Quantity","SubType":"Number"},{"Name":"Troubleshooting","WikipediaUrl":null,"BingId":null,"Type":null,"SubType":null},{"Name":"Id Software","WikipediaUrl":null,"BingId":null,"Type":null,"SubType":null},{"Name":"System Center Data Protection Manager","WikipediaUrl":null,"BingId":null,"Type":null,"SubType":null},{"Name":"Microsoft Power BI","WikipediaUrl":null,"BingId":null,"Type":"Organization","SubType":null},{"Name":"Microsoft System Center Configuration Manager","WikipediaUrl":null,"BingId":null,"Type":null,"SubType":null},{"Name":"Gerry Hampson","WikipediaUrl":null,"BingId":null,"Type":"Person","SubType":null},{"Name":"Power BI","WikipediaUrl":null,"BingId":null,"Type":null,"SubType":null},{"Name":"2007","WikipediaUrl":null,"BingId":null,"Type":"DateTime","SubType":"DateRange"},{"Name":"2012","WikipediaUrl":null,"BingId":null,"Type":"DateTime","SubType":"DateRange"},{"Name":"Guru","WikipediaUrl":null,"BingId":null,"Type":"Location","SubType":null},{"Name":"Transact-SQL","WikipediaUrl":null,"BingId":null,"Type":null,"SubType":null},{"Name":"Sorting algorithm","WikipediaUrl":null,"BingId":null,"Type":null,"SubType":null},{"Name":"Ronen Ariely","WikipediaUrl":null,"BingId":null,"Type":"Person","SubType":null},{"Name":"Read (system call)","WikipediaUrl":null,"BingId":null,"Type":null,"SubType":null},{"Name":"Cut, copy, and paste","WikipediaUrl":null,"BingId":null,"Type":null,"SubType":null},{"Name":"Database","WikipediaUrl":null,"BingId":null,"Type":null,"SubType":null},{"Name":"SQL Agent Job","WikipediaUrl":null,"BingId":null,"Type":"Organization","SubType":null},{"Name":"Synonym (database)","WikipediaUrl":null,"BingId":null,"Type":null,"SubType":null},{"Name":"Saeid\r\n Hasani \r\nVisual Basic\r\nThe TechNet Guru","WikipediaUrl":null,"BingId":null,"Type":"Organization","SubType":null},{"Name":"Database trigger","WikipediaUrl":null,"BingId":null,"Type":null,"SubType":null},{"Name":"SQL","WikipediaUrl":null,"BingId":null,"Type":null,"SubType":null},{"Name":"Visual Basic","WikipediaUrl":null,"BingId":null,"Type":null,"SubType":null},{"Name":"POST (HTTP)","WikipediaUrl":null,"BingId":null,"Type":null,"SubType":null},{"Name":"Wiki","WikipediaUrl":null,"BingId":null,"Type":null,"SubType":null},{"Name":"Visual Basic","WikipediaUrl":null,"BingId":null,"Type":"Organization","SubType":null},{"Name":"Image resolution","WikipediaUrl":null,"BingId":null,"Type":null,"SubType":null},{"Name":"Chart","WikipediaUrl":null,"BingId":null,"Type":null,"SubType":null},{"Name":"Sort (Unix)","WikipediaUrl":null,"BingId":null,"Type":null,"SubType":null},{"Name":"Filter (software)","WikipediaUrl":null,"BingId":null,"Type":null,"SubType":null},{"Name":"Comma-separated values","WikipediaUrl":null,"BingId":null,"Type":null,"SubType":null},{"Name":"Emiliano Musso \r\nVisual C#\r\n\r\nThe TechNet Guru","WikipediaUrl":null,"BingId":null,"Type":"Organization","SubType":null},{"Name":"Microsoft Visual C++","WikipediaUrl":null,"BingId":null,"Type":null,"SubType":null},{"Name":"Generic top-level domain","WikipediaUrl":null,"BingId":null,"Type":null,"SubType":null},{"Name":"Windows Service","WikipediaUrl":null,"BingId":null,"Type":"Organization","SubType":null},{"Name":"Printing","WikipediaUrl":null,"BingId":null,"Type":null,"SubType":null},{"Name":"Windows service","WikipediaUrl":null,"BingId":null,"Type":null,"SubType":null},{"Name":"Yan Grenier","WikipediaUrl":null,"BingId":null,"Type":"Person","SubType":null},{"Name":"WCF","WikipediaUrl":null,"BingId":null,"Type":"Organization","SubType":null},{"Name":"Tom Mohan","WikipediaUrl":null,"BingId":null,"Type":"Person","SubType":null},{"Name":"Universal Windows Apps\r\nThe TechNet Guru","WikipediaUrl":null,"BingId":null,"Type":"Organization","SubType":null},{"Name":"Universal Windows Platform apps","WikipediaUrl":null,"BingId":null,"Type":null,"SubType":null},{"Name":"Windows Phone","WikipediaUrl":null,"BingId":null,"Type":null,"SubType":null},{"Name":"Mechanical advantage","WikipediaUrl":null,"BingId":null,"Type":null,"SubType":null},{"Name":"UI","WikipediaUrl":null,"BingId":null,"Type":"Organization","SubType":null},{"Name":"Continuum (measurement)","WikipediaUrl":null,"BingId":null,"Type":null,"SubType":null},{"Name":"User interface","WikipediaUrl":null,"BingId":null,"Type":null,"SubType":null},{"Name":"Computer mouse","WikipediaUrl":null,"BingId":null,"Type":null,"SubType":null},{"Name":"Computer keyboard","WikipediaUrl":null,"BingId":null,"Type":null,"SubType":null},{"Name":"Lee McPherson","WikipediaUrl":null,"BingId":null,"Type":"Person","SubType":null},{"Name":"Web server","WikipediaUrl":null,"BingId":null,"Type":null,"SubType":null},{"Name":"Emiliano Musso\r\nUnderstanding\r\n UAP","WikipediaUrl":null,"BingId":null,"Type":"Organization","SubType":null},{"Name":"User Account Control","WikipediaUrl":null,"BingId":null,"Type":null,"SubType":null},{"Name":"Building Universal Apps","WikipediaUrl":null,"BingId":null,"Type":"Organization","SubType":null},{"Name":"Building","WikipediaUrl":null,"BingId":null,"Type":null,"SubType":null},{"Name":"2015","WikipediaUrl":null,"BingId":null,"Type":"DateTime","SubType":"DateRange"},{"Name":"Sumantro","WikipediaUrl":null,"BingId":null,"Type":"Organization","SubType":null},{"Name":"Windows 10","WikipediaUrl":null,"BingId":null,"Type":null,"SubType":null},{"Name":"Software development","WikipediaUrl":null,"BingId":null,"Type":null,"SubType":null},{"Name":"Sumantro Architecture of Windows","WikipediaUrl":null,"BingId":null,"Type":"Organization","SubType":null},{"Name":"Computer architecture","WikipediaUrl":null,"BingId":null,"Type":null,"SubType":null},{"Name":"Windows Runtime","WikipediaUrl":null,"BingId":null,"Type":null,"SubType":null},{"Name":"Pooja Baraskar","WikipediaUrl":null,"BingId":null,"Type":null,"SubType":null},{"Name":"8.1","WikipediaUrl":null,"BingId":null,"Type":"Quantity","SubType":"Number"},{"Name":"Windows Runtime XAML Framework","WikipediaUrl":null,"BingId":null,"Type":null,"SubType":null},{"Name":"Universal Windows Platform apps","WikipediaUrl":null,"BingId":null,"Type":null,"SubType":null},{"Name":"Programmer","WikipediaUrl":null,"BingId":null,"Type":null,"SubType":null},{"Name":"Video game development","WikipediaUrl":null,"BingId":null,"Type":null,"SubType":null},{"Name":"Games for Windows","WikipediaUrl":null,"BingId":null,"Type":null,"SubType":null},{"Name":"DirectX","WikipediaUrl":null,"BingId":null,"Type":null,"SubType":null},{"Name":"Sumantro\r\nProject Spartan For Developers","WikipediaUrl":null,"BingId":null,"Type":"Organization","SubType":null},{"Name":"Microsoft Edge","WikipediaUrl":null,"BingId":null,"Type":null,"SubType":null},{"Name":"Infinite loop","WikipediaUrl":null,"BingId":null,"Type":null,"SubType":null},{"Name":"Pooja Baraskar\r\n\r\nWindows PowerShell\r\nThe TechNet Guru","WikipediaUrl":null,"BingId":null,"Type":"Organization","SubType":null},{"Name":"PowerShell","WikipediaUrl":null,"BingId":null,"Type":null,"SubType":null},{"Name":"Guru (2007 film)","WikipediaUrl":null,"BingId":null,"Type":null,"SubType":null},{"Name":"Wiki","WikipediaUrl":null,"BingId":null,"Type":null,"SubType":null},{"Name":"2012","WikipediaUrl":null,"BingId":null,"Type":"DateTime","SubType":"DateRange"},{"Name":"System Center Operations Manager","WikipediaUrl":null,"BingId":null,"Type":null,"SubType":null},{"Name":"SharePoint","WikipediaUrl":null,"BingId":null,"Type":null,"SubType":null},{"Name":"Web content","WikipediaUrl":null,"BingId":null,"Type":null,"SubType":null},{"Name":"PowerShell","WikipediaUrl":null,"BingId":null,"Type":null,"SubType":null},{"Name":"Arleta Wanat\r\nManage SharePoint Online Access","WikipediaUrl":null,"BingId":null,"Type":"Organization","SubType":null},{"Name":"Internet","WikipediaUrl":null,"BingId":null,"Type":null,"SubType":null},{"Name":"Microsoft Access","WikipediaUrl":null,"BingId":null,"Type":null,"SubType":null},{"Name":"Arleta\r\n Wanat \r\nWindows Presentation Foundation","WikipediaUrl":null,"BingId":null,"Type":"Organization","SubType":null},{"Name":"Windows Presentation Foundation","WikipediaUrl":null,"BingId":null,"Type":null,"SubType":null},{"Name":"Guru","WikipediaUrl":null,"BingId":null,"Type":"Location","SubType":null},{"Name":"Generic top-level domain","WikipediaUrl":null,"BingId":null,"Type":null,"SubType":null},{"Name":"POST (HTTP)","WikipediaUrl":null,"BingId":null,"Type":null,"SubType":null},{"Name":"Wiki","WikipediaUrl":null,"BingId":null,"Type":null,"SubType":null},{"Name":"Dependency Property Default Double Trouble","WikipediaUrl":null,"BingId":null,"Type":"Organization","SubType":null},{"Name":"Andy ONeill","WikipediaUrl":null,"BingId":null,"Type":"Person","SubType":null},{"Name":"Property","WikipediaUrl":null,"BingId":null,"Type":null,"SubType":null},{"Name":"Default (finance)","WikipediaUrl":null,"BingId":null,"Type":null,"SubType":null},{"Name":"Andy ONeill\r\nData Input Validation","WikipediaUrl":null,"BingId":null,"Type":"Organization","SubType":null},{"Name":"Data","WikipediaUrl":null,"BingId":null,"Type":null,"SubType":null},{"Name":"Data validation","WikipediaUrl":null,"BingId":null,"Type":null,"SubType":null},{"Name":"Intelligent Network","WikipediaUrl":null,"BingId":null,"Type":null,"SubType":null},{"Name":"Tom Mohan \r\nWindows Server","WikipediaUrl":null,"BingId":null,"Type":"Person","SubType":null},{"Name":"Windows Server","WikipediaUrl":null,"BingId":null,"Type":null,"SubType":null},{"Name":".by","WikipediaUrl":null,"BingId":null,"Type":null,"SubType":null},{"Name":"Darshana Jayathilake","WikipediaUrl":null,"BingId":null,"Type":"Person","SubType":null},{"Name":"How (book)","WikipediaUrl":null,"BingId":null,"Type":null,"SubType":null},{"Name":"Shared resource","WikipediaUrl":null,"BingId":null,"Type":null,"SubType":null},{"Name":"Non (comics)","WikipediaUrl":null,"BingId":null,"Type":null,"SubType":null},{"Name":"Manjunath Sullad Active","WikipediaUrl":null,"BingId":null,"Type":"Organization","SubType":null},{"Name":"Active Directory","WikipediaUrl":null,"BingId":null,"Type":null,"SubType":null},{"Name":"Richard Mueller","WikipediaUrl":null,"BingId":null,"Type":"Person","SubType":null},{"Name":"Portals\r\nThe TechNet Guru","WikipediaUrl":null,"BingId":null,"Type":"Organization","SubType":null},{"Name":"Wiki","WikipediaUrl":null,"BingId":null,"Type":null,"SubType":null},{"Name":"Web portal","WikipediaUrl":null,"BingId":null,"Type":null,"SubType":null},{"Name":"Generic top-level domain","WikipediaUrl":null,"BingId":null,"Type":null,"SubType":null},{"Name":"POST (HTTP)","WikipediaUrl":null,"BingId":null,"Type":null,"SubType":null},{"Name":"Technet WIki Guru CompetitionbyAndy\r\n ONeill \r\nMiscellaneous\r\nThe TechNet Guru","WikipediaUrl":null,"BingId":null,"Type":"Organization","SubType":null},{"Name":"Arduino Uno","WikipediaUrl":null,"BingId":null,"Type":"Organization","SubType":null},{"Name":"Read (system call)","WikipediaUrl":null,"BingId":null,"Type":null,"SubType":null},{"Name":"Carmelo La Monica","WikipediaUrl":null,"BingId":null,"Type":"Person","SubType":null},{"Name":"Arduino","WikipediaUrl":null,"BingId":null,"Type":null,"SubType":null},{"Name":"Microsoft Office SwaybyDanish\r\n Islam Moisture","WikipediaUrl":null,"BingId":null,"Type":"Organization","SubType":null},{"Name":"Microsoft Office","WikipediaUrl":null,"BingId":null,"Type":null,"SubType":null},{"Name":"Islam in the Philippines","WikipediaUrl":null,"BingId":null,"Type":null,"SubType":null},{"Name":"Pooja Baraskar\r\nWindows 8.1 App Development","WikipediaUrl":null,"BingId":null,"Type":"Organization","SubType":null},{"Name":"Microsoft Windows","WikipediaUrl":null,"BingId":null,"Type":null,"SubType":null},{"Name":"Intel Galileo","WikipediaUrl":null,"BingId":null,"Type":null,"SubType":null},{"Name":"Windows 8.1","WikipediaUrl":null,"BingId":null,"Type":null,"SubType":null},{"Name":"Mobile app development","WikipediaUrl":null,"BingId":null,"Type":null,"SubType":null},{"Name":"HTML5","WikipediaUrl":null,"BingId":null,"Type":null,"SubType":null},{"Name":"Cascading Style Sheets","WikipediaUrl":null,"BingId":null,"Type":null,"SubType":null},{"Name":"Guru","WikipediaUrl":null,"BingId":null,"Type":"Location","SubType":null},{"Name":"JavaScript","WikipediaUrl":null,"BingId":null,"Type":null,"SubType":null},{"Name":"Microsoft TechNet","WikipediaUrl":null,"BingId":null,"Type":null,"SubType":null},{"Name":"Award Software","WikipediaUrl":null,"BingId":null,"Type":null,"SubType":null},{"Name":"Article (publishing)","WikipediaUrl":null,"BingId":null,"Type":null,"SubType":null},{"Name":"This Month","WikipediaUrl":null,"BingId":null,"Type":"DateTime","SubType":"DateRange"},{"Name":"Internet forum","WikipediaUrl":null,"BingId":null,"Type":null,"SubType":null},{"Name":"Microsoft BizTalk Server","WikipediaUrl":null,"BingId":null,"Type":null,"SubType":null},{"Name":"FIM","WikipediaUrl":null,"BingId":null,"Type":"Quantity","SubType":"Currency"},{"Name":"Forefront Identity Manager","WikipediaUrl":null,"BingId":null,"Type":null,"SubType":null},{"Name":"Power Pivot","WikipediaUrl":null,"BingId":null,"Type":null,"SubType":null},{"Name":"PowerShell","WikipediaUrl":null,"BingId":null,"Type":null,"SubType":null},{"Name":"SharePoint","WikipediaUrl":null,"BingId":null,"Type":null,"SubType":null},{"Name":"Microsoft Small Basic","WikipediaUrl":null,"BingId":null,"Type":null,"SubType":null},{"Name":"Microsoft SQL Server","WikipediaUrl":null,"BingId":null,"Type":null,"SubType":null},{"Name":".ss","WikipediaUrl":null,"BingId":null,"Type":null,"SubType":null},{"Name":"Order of the British Empire","WikipediaUrl":null,"BingId":null,"Type":null,"SubType":null},{"Name":"Microsoft Analysis Services","WikipediaUrl":null,"BingId":null,"Type":null,"SubType":null},{"Name":"SQL Server Integration Services","WikipediaUrl":null,"BingId":null,"Type":null,"SubType":null},{"Name":"SQL Server Reporting Services","WikipediaUrl":null,"BingId":null,"Type":null,"SubType":null},{"Name":"System Center\r\nSystem Center\r\nSystem Center\r\nSystem Center\r\nSystem Center\r\nSystem Center\r\nSystem Center\r\nSystem Center\r\nTN Wiki","WikipediaUrl":null,"BingId":null,"Type":"Organization","SubType":null},{"Name":"Operating system","WikipediaUrl":null,"BingId":null,"Type":null,"SubType":null},{"Name":"Center (group theory)","WikipediaUrl":null,"BingId":null,"Type":null,"SubType":null},{"Name":".tn","WikipediaUrl":null,"BingId":null,"Type":null,"SubType":null},{"Name":"Wiki","WikipediaUrl":null,"BingId":null,"Type":null,"SubType":null},{"Name":"Transact-SQL","WikipediaUrl":null,"BingId":null,"Type":null,"SubType":null},{"Name":"VB\r\nVisio\r\nWindows Phone\r\nWindows Server\r\nWindows Server\r\nWindows Server\r\nWindows Server","WikipediaUrl":null,"BingId":null,"Type":"Organization","SubType":null},{"Name":"Visual Basic","WikipediaUrl":null,"BingId":null,"Type":null,"SubType":null},{"Name":"Microsoft Visio","WikipediaUrl":null,"BingId":null,"Type":null,"SubType":null},{"Name":"Windows Phone","WikipediaUrl":null,"BingId":null,"Type":null,"SubType":null},{"Name":"Windows Server","WikipediaUrl":null,"BingId":null,"Type":null,"SubType":null},{"Name":"Windows Presentation Foundation","WikipediaUrl":null,"BingId":null,"Type":null,"SubType":null}],"GitHubFileNameAndExtension":"30963.technet-guru-contributions-may-2015.html"}