{"Name":"Enterprise Mobility","Variations":{"Enterprise Mobility":{"Variation":null,"Mentions":0,"Refs":[{"Title":"User Page: Richard Mueller - TechNet Articles - United States (English) - TechNet Wiki","FileName":"31616.user-page-richard-mueller.html","Mentions":2},{"Title":"User Page: CloudCrusader - TechNet Articles - United States (English) - TechNet Wiki","FileName":"39800.user-page-cloudcrusader.html","Mentions":2}]}},"FileName":"enterprise mobility.json","Refs":[{"Title":"User Page: Richard Mueller - TechNet Articles - United States (English) - TechNet Wiki","FileName":"31616.user-page-richard-mueller.html","Mentions":2},{"Title":"User Page: CloudCrusader - TechNet Articles - United States (English) - TechNet Wiki","FileName":"39800.user-page-cloudcrusader.html","Mentions":2}],"ShowAsTag":false,"IsPersonalised":false,"Mentions":4,"Notes":null}