{"Name":"filted data tree structure","Variations":{"filted data tree structure":{"Variation":null,"Mentions":0,"Refs":[{"Title":"IoT Suite - Under The Hood - Remote Monitoring - TechNet Articles - United States (English) - TechNet Wiki","FileName":"32941.iot-suite-under-the-hood-remote-monitoring.html","Mentions":1}]}},"FileName":"filted data tree structure.json","Refs":[{"Title":"IoT Suite - Under The Hood - Remote Monitoring - TechNet Articles - United States (English) - TechNet Wiki","FileName":"32941.iot-suite-under-the-hood-remote-monitoring.html","Mentions":1}],"ShowAsTag":false,"IsPersonalised":false,"Mentions":1,"Notes":null}