{"Name":"forward thinking","Variations":{"forward thinking":{"Variation":null,"Mentions":0,"Refs":[{"Title":"Template Method Design Pattern - TechNet Articles - United States (English) - TechNet Wiki","FileName":"13232.template-method-design-pattern.html","Mentions":1}]}},"FileName":"forward thinking.json","Refs":[{"Title":"Template Method Design Pattern - TechNet Articles - United States (English) - TechNet Wiki","FileName":"13232.template-method-design-pattern.html","Mentions":1}],"ShowAsTag":false,"IsPersonalised":false,"Mentions":1,"Notes":null}