{"Name":"John","Variations":{"John":{"Variation":null,"Mentions":0,"Refs":[{"Title":"Azure Cognitive Services - Computer Vision - Face Recognition API - Identify and search all your photos for FREE! - TechNet Articles - United States (English) - TechNet Wiki","FileName":"51563.azure-cognitive-services-computer-vision-face-recognition-api-identify-and-search-all-your-photos-for-free.html","Mentions":1},{"Title":"TechNet Guru Contributions - August 2015 - TechNet Articles - United States (English) - TechNet Wiki","FileName":"31735.technet-guru-contributions-august-2015.html","Mentions":1},{"Title":"TechNet Guru Contributions - December 2014 - TechNet Articles - United States (English) - TechNet Wiki","FileName":"28664.technet-guru-contributions-december-2014.html","Mentions":1}]}},"FileName":"john.json","Refs":[{"Title":"Azure Cognitive Services - Computer Vision - Face Recognition API - Identify and search all your photos for FREE! - TechNet Articles - United States (English) - TechNet Wiki","FileName":"51563.azure-cognitive-services-computer-vision-face-recognition-api-identify-and-search-all-your-photos-for-free.html","Mentions":1},{"Title":"TechNet Guru Contributions - August 2015 - TechNet Articles - United States (English) - TechNet Wiki","FileName":"31735.technet-guru-contributions-august-2015.html","Mentions":1},{"Title":"TechNet Guru Contributions - December 2014 - TechNet Articles - United States (English) - TechNet Wiki","FileName":"28664.technet-guru-contributions-december-2014.html","Mentions":1}],"ShowAsTag":false,"IsPersonalised":false,"Mentions":3,"Notes":null}