{"Name":"LIST SQLSERVER USER DATABASES","Variations":{"LIST SQLSERVER USER DATABASES":{"Variation":null,"Mentions":0,"Refs":[{"Title":"User Page: Prashanth Jayaram - TechNet Articles - United States (English) - TechNet Wiki","FileName":"34953.user-page-prashanth-jayaram.html","Mentions":1}]}},"FileName":"list sqlserver user databases.json","Refs":[{"Title":"User Page: Prashanth Jayaram - TechNet Articles - United States (English) - TechNet Wiki","FileName":"34953.user-page-prashanth-jayaram.html","Mentions":1}],"ShowAsTag":false,"IsPersonalised":false,"Mentions":1,"Notes":null}