{"Name":"MSDTC","Variations":{"MSDTC":{"Variation":null,"Mentions":0,"Refs":[{"Title":"User Page: Durval Ramos - TechNet Articles - United States (English) - TechNet Wiki","FileName":"28258.user-page-durval-ramos.html","Mentions":1},{"Title":"TechNet Guru Contributions - August 2014 - TechNet Articles - United States (English) - TechNet Wiki","FileName":"25746.technet-guru-contributions-august-2014.html","Mentions":1}]}},"FileName":"msdtc.json","Refs":[{"Title":"User Page: Durval Ramos - TechNet Articles - United States (English) - TechNet Wiki","FileName":"28258.user-page-durval-ramos.html","Mentions":1},{"Title":"TechNet Guru Contributions - August 2014 - TechNet Articles - United States (English) - TechNet Wiki","FileName":"25746.technet-guru-contributions-august-2014.html","Mentions":1}],"ShowAsTag":false,"IsPersonalised":false,"Mentions":2,"Notes":null}